[
  {
    "text": "అడిగిన జీతంబు ఇయ్యని రాజు\nకొడుకులను పెండ్లాడిన కోడలు\nముడిచిన సొమ్ములకే ముద్దైన భార్య\nనడవడి లేని పతి యొద్ద నచ్చాము సుమతీ",
    "title": "సుమతీ శతకం 2",
    "author": "బద్దెన",
    "style": "కందం",
    "era": "14వ శతాబ్దం",
    "language": "telugu"
  },
  {
    "text": "పలుకే బంగారమాయె\nపలకరించే వారెవరు\nరామ నామం చాలు నాకు\nమోక్షమార్గం దొరికెను",
    "title": "రామదాసు కీర్తన 3",
    "author": "రామదాసు",
    "style": "భక్తి కీర్తన",
    "era": "17వ శతాబ్దం",
    "language": "telugu"
  },
  {
    "text": "పండితుడు అడవిలో ఉన్నా గౌరవం పొందుతాడు\nమూర్ఖుడు రాజసభలో ఉన్నా అవమానం పొందుతాడు\nవిద్య ఉన్నచోట విజయం ఉంటుంది\nభర్తృహరి సత్యవాక్యం",
    "title": "భర్తృహరి సుభాషితం 10",
    "author": "భర్తృహరి",
    "style": "సుభాషిత శతకం",
    "era": "ప్రాచీన",
    "language": "telugu"
  },
  {
    "text": "నేను నేర్చిన పాఠాలు\nజీవితం నేర్పించింది\nకష్టాల్లో నేర్చిన విద్య\nసుఖాల్లో గుర్తుండు",
    "title": "ఆధునిక కవిత 16",
    "author": "ఆధునిక కవి",
    "style": "వచన కవిత",
    "era": "21వ శతాబ్దం",
    "language": "telugu"
  },
  {
    "text": "నిత్యకల్యాణము నిరంతరము\nపచ్చ తోరణాలు పండగ వాతావరణము\nతిరుమలలో ఉత్సవాలు దివ్యమయ్యను",
    "title": "అన్నమయ్య కీర్తన 24",
    "author": "అన్నమయ్య",
    "style": "సంకీర్తన",
    "era": "15వ శతాబ్దం",
    "language": "telugu"
  },
  {
    "text": "మహాకవుల సరసన మహాకవిగా నిలిచెను\nతెలుగు సాహిత్యంలో తేజస్సుగా వెలిగెను\nకవిత్రయమునకు కావ్య వారసుడాయెను\nశ్రీనాథుడు సాహిత్య సార్వభౌముడు",
    "title": "శ్రీనాథ పద్యం 23",
    "author": "శ్రీనాథుడు",
    "style": "ప్రబంధం",
    "era": "15వ శతాబ్దం",
    "language": "telugu"
  },
  {
    "text": "పంచరత్న కృతులందు\nపరమపద సోపానం\nరామభక్తి రాగాలలో\nరసమయంగా వెలిగెను",
    "title": "త్యాగరాజ కీర్తన 18",
    "author": "త్యాగరాజు",
    "style": "కర్ణాటక సంగీతం",
    "era": "18వ శతాబ్దం",
    "language": "telugu"
  },
  {
    "text": "ధైర్యంగా ఉండు దుర్మార్గాన్ని ఎదుర్కో\nపిరికితనం పనికిరాదు",
    "title": "నీతి పద్యం 23",
    "author": "సంప్రదాయ",
    "style": "నీతి శతకం",
    "era": "సంప్రదాయ",
    "language": "telugu"
  },
  {
    "text": "సీతారామ కల్యాణం\nభద్రాచలంలో భాగ్యం\nరామదాసు ఆశీస్సులతో\nరామ భక్తి ఫలిస్తుంది",
    "title": "రామదాసు కీర్తన 15",
    "author": "రామదాసు",
    "style": "భక్తి కీర్తన",
    "era": "17వ శతాబ్దం",
    "language": "telugu"
  },
  {
    "text": "శృంగార నైషధం\nమధుర శృంగారం\nప్రణయ కావ్యం\nరసమయ రచన",
    "title": "శ్రీనాథ పద్యం 12",
    "author": "శ్రీనాథుడు",
    "style": "ప్రబంధం",
    "era": "15వ శతాబ్దం",
    "language": "telugu"
  },
  {
    "text": "భీష్మ ద్రోణ కర్ణులు\nమహావీరుల చరిత్రలు\nనన్నయ కావ్యంలో\nనయనానందంగా చూపెను",
    "title": "నన్నయ పద్యం 20",
    "author": "నన్నయ",
    "style": "మహాభారతం",
    "era": "11వ శతాబ్దం",
    "language": "telugu"
  },
  {
    "text": "ఇంటర్నెట్ యుగంలో ఇప్పుడు\nసమాచారం వేళ్ళ కొసలో\nజాగ్రత్తగా ఉపయోగించు\nమంచికి వాడుకో",
    "title": "ఆధునిక కవిత 36",
    "author": "ఆధునిక కవి",
    "style": "వచన కవిత",
    "era": "21వ శతాబ్దం",
    "language": "telugu"
  },
  {
    "text": "నేను సైతం ప్రపంచాన్ని\nప్రేమిస్తున్నాను\nప్రజల కష్టాలను కనిపెడుతూ\nపోరాట గీతం పాడుతూ",
    "title": "శ్రీశ్రీ కవిత 2",
    "author": "శ్రీశ్రీ",
    "style": "అభ్యుదయ కవిత్వం",
    "era": "20వ శతాబ్దం",
    "language": "telugu"
  },
  {
    "text": "తినగ తినగ వేము తీయనౌను కూడ\nచదువ చదువ జ్ఞానము చేరువచ్చు\nసాధన వలన సకలము సిద్ధించు\nసాధనమే మూలము సుమతీ",
    "title": "సుమతీ శతకం 20",
    "author": "బద్దెన",
    "style": "కందం",
    "era": "14వ శతాబ్దం",
    "language": "telugu"
  },
  {
    "text": "మరో ప్రపంచం మనకు కావాలి\nమార్పు రావాలి సమాజంలో\nపేదరికం పోవాలి\nసమానత్వం రావాలి",
    "title": "శ్రీశ్రీ కవిత 5",
    "author": "శ్రీశ్రీ",
    "style": "అభ్యుదయ కవిత్వం",
    "era": "20వ శతాబ్దం",
    "language": "telugu"
  },
  {
    "text": "రోబోలు మానవులకు సాయం\nఆర్టిఫిషియల్ ఇంటెలిజెన్స్ అద్భుతం\nభవిష్యత్తు టెక్నాలజీది\nమానవత్వం మరువకు",
    "title": "ఆధునిక కవిత 40",
    "author": "ఆధునిక కవి",
    "style": "వచన కవిత",
    "era": "21వ శతాబ్దం",
    "language": "telugu"
  },
  {
    "text": "హాస్య రచనలు\nచిలకమర్తి శైలి\nవినోదం అందించు\nబోధన చేయు",
    "title": "చిలకమర్తి రచన 3",
    "author": "చిలకమర్తి",
    "style": "హాస్య కవిత్వం",
    "era": "20వ శతాబ్దం",
    "language": "telugu"
  },
  {
    "text": "భీష్ముని శరతల్పం\nద్రోణుని అస్త్ర విద్య\nకర్ణుని కవచ కుండలాలు\nతిక్కన పద్యాలలో తెలియజేసెను",
    "title": "తిక్కన పద్యం 21",
    "author": "తిక్కన",
    "style": "మహాభారతం",
    "era": "13వ శతాబ్దం",
    "language": "telugu"
  },
  {
    "text": "ఆది పర్వం సభా పర్వం అరణ్య పర్వం\nమూడు పర్వాలు రచించెను\nవ్యాస భారతాన్ని వచన పద్యాలలో\nతెలుగు తల్లికి అందించెను",
    "title": "నన్నయ పద్యం 3",
    "author": "నన్నయ",
    "style": "మహాభారతం",
    "era": "11వ శతాబ్దం",
    "language": "telugu"
  },
  {
    "text": "నారాయణ నారాయణ\nనా మది నీవే నారాయణ\nసురలక నీవే నారాయణ\nపరమపురుష నారాయణ",
    "title": "అన్నమయ్య కీర్తన 5",
    "author": "అన్నమయ్య",
    "style": "సంకీర్తన",
    "era": "15వ శతాబ్దం",
    "language": "telugu"
  },
  {
    "text": "మద్య మాంసములను మానినంత మేలు\nపొగ తాగు పొగలు పొడిచిపోవు\nమత్తు మందులన్ని మానవుని చెరిచు\nవిశ్వదాభిరామ వినురవేమ",
    "title": "వేమన పద్యం 22",
    "author": "వేమన",
    "style": "ఆట వెలది",
    "era": "18వ శతాబ్దం",
    "language": "telugu"
  },
  {
    "text": "నవ్య సాహిత్యంలో నాయకుడు\nకొత్త దారులు చూపించెను\nపాత పద్ధతులు వదిలి\nప్రగతి మార్గం చూపెను",
    "title": "గురజాడ కవిత 19",
    "author": "గురజాడ అప్పారావు",
    "style": "సామాజిక కవిత్వం",
    "era": "20వ శతాబ్దం",
    "language": "telugu"
  },
  {
    "text": "విద్యా విలువలు\nనేర్చుకోవాలి\nమంచి మార్గంలో\nనడవాలి",
    "title": "చిలకమర్తి రచన 6",
    "author": "చిలకమర్తి",
    "style": "హాస్య కవిత్వం",
    "era": "20వ శతాబ్దం",
    "language": "telugu"
  },
  {
    "text": "క్రోధము శత్రువు క్షమ మిత్రుడు\nలోభము దోషము దానం గుణము",
    "title": "నీతి పద్యం 6",
    "author": "సంప్రదాయ",
    "style": "నీతి శతకం",
    "era": "సంప్రదాయ",
    "language": "telugu"
  },
  {
    "text": "గరుడసేవలో గరుడునెక్కి స్వామి\nభక్తులకు దర్శనమిచ్చి భాగ్యమిచ్చేను\nవాహనసేవలో వైభవమందు",
    "title": "అన్నమయ్య కీర్తన 25",
    "author": "అన్నమయ్య",
    "style": "సంకీర్తన",
    "era": "15వ శతాబ్దం",
    "language": "telugu"
  },
  {
    "text": "కలలు కనడం తప్పు కాదు\nకలలను సాధించడం గొప్పది\nఆశలు పెట్టుకోవడం మంచిది\nఆశలను నేరవేర్చుకోవడం అద్భుతం",
    "title": "ఆధునిక కవిత 14",
    "author": "ఆధునిక కవి",
    "style": "వచన కవిత",
    "era": "21వ శతాబ్దం",
    "language": "telugu"
  },
  {
    "text": "పుస్తకం మంచి మిత్రుడు\nజ్ఞానం ఇచ్చే గురువు\nచదువు జీవిత వెలుగు\nవిద్య సర్వ సంపద",
    "title": "ఆధునిక కవిత 20",
    "author": "ఆధునిక కవి",
    "style": "వచన కవిత",
    "era": "21వ శతాబ్దం",
    "language": "telugu"
  },
  {
    "text": "పల్లెటూరి అందాలు పట్టణంలో కనరావు\nపంట చేల పరిమళం పట్టుకోలేము\nఆకురాల్లు పక్షుల పాట వినలేము\nప్రకృతి ఒడిలో పరవశం పొందలేము",
    "title": "ఆధునిక కవిత 10",
    "author": "ఆధునిక కవి",
    "style": "వచన కవిత",
    "era": "21వ శతాబ్దం",
    "language": "telugu"
  },
  {
    "text": "తెలుగు భాష అందాలు\nతీయని పదాలలో\nకృష్ణశాస్త్రి కవిత్వంలో\nకనబడే మాధుర్యం",
    "title": "కృష్ణశాస్త్రి కవిత 19",
    "author": "దేవులపల్లి కృష్ణశాస్త్రి",
    "style": "భావ కవిత్వం",
    "era": "20వ శతాబ్దం",
    "language": "telugu"
  },
  {
    "text": "భక్తి సంగీతంలో భాస్కరుడు\nరాగాలలో రామ నామ స్మరణ\nకృతులలో కరుణ రసం\nత్యాగరాజు సంగీత వైభవం",
    "title": "త్యాగరాజ కీర్తన 23",
    "author": "త్యాగరాజు",
    "style": "కర్ణాటక సంగీతం",
    "era": "18వ శతాబ్దం",
    "language": "telugu"
  },
  {
    "text": "గోదావరి గంగమ్మా\nకృష్ణవేణి అక్కమ్మా\nనదులన్నీ అమ్మలమ్మా\nజీవనది తల్లమ్మా",
    "title": "జానపద గేయం 15",
    "author": "జానపద",
    "style": "గేయం",
    "era": "సంప్రదాయ",
    "language": "telugu"
  },
  {
    "text": "యువతకు సందేశం\nదేశం మీ చేతుల్లో\nభవిష్యత్తు నిర్మించండి\nసమాజం మారిస్తారు",
    "title": "ఆధునిక కవిత 25",
    "author": "ఆధునిక కవి",
    "style": "వచన కవిత",
    "era": "21వ శతాబ్దం",
    "language": "telugu"
  },
  {
    "text": "ఉదయం లేచి సూర్యునికి నమస్కారం\nసాయంత్రం చందమామకు వందనం\nరాత్రి నక్షత్రాలతో సంభాషణ\nప్రకృతితో మనిషి స్నేహం",
    "title": "ఆధునిక కవిత 9",
    "author": "ఆధునిక కవి",
    "style": "వచన కవిత",
    "era": "21వ శతాబ్దం",
    "language": "telugu"
  },
  {
    "text": "గ్రంథాలయం జ్ఞానసాగరం\nపుస్తకాలు విజ్ఞాన నిధులు\nచదువు చదువు చదువు నేర్చుకో\nజీవితంలో విజయం సాధించు",
    "title": "ఆధునిక కవిత 11",
    "author": "ఆధునిక కవి",
    "style": "వచన కవిత",
    "era": "21వ శతాబ్దం",
    "language": "telugu"
  },
  {
    "text": "వేద వేదాంగాలు నేర్చిన విద్వాంసుడు\nశబ్దశాస్త్రంలో శ్రేష్ఠుడు\nఛందస్సు వ్యాకరణంలో\nచతురత చూపిన మహాకవి",
    "title": "నన్నయ పద్యం 11",
    "author": "నన్నయ",
    "style": "మహాభారతం",
    "era": "11వ శతాబ్దం",
    "language": "telugu"
  },
  {
    "text": "లడ్డూ ప్రసాదమిచ్చి లాలించేను\nస్వామి కృపారసమిది స్వీకరించు\nప్రసాదమందు ప్రభువు ప్రేమమందు",
    "title": "అన్నమయ్య కీర్తన 19",
    "author": "అన్నమయ్య",
    "style": "సంకీర్తన",
    "era": "15వ శతాబ్దం",
    "language": "telugu"
  },
  {
    "text": "కర్ణాటక సంగీతంలో\nకమనీయమైన కీర్తనలు\nత్యాగరాజ ముద్రికలో\nతేజస్సుగా వెలిగెను",
    "title": "త్యాగరాజ కీర్తన 20",
    "author": "త్యాగరాజు",
    "style": "కర్ణాటక సంగీతం",
    "era": "18వ శతాబ్దం",
    "language": "telugu"
  },
  {
    "text": "ధనంజయ విజయం\nవీర రసం\nయుద్ధ వర్ణన\nధీర కథనం",
    "title": "శ్రీనాథ పద్యం 13",
    "author": "శ్రీనాథుడు",
    "style": "ప్రబంధం",
    "era": "15వ శతాబ్దం",
    "language": "telugu"
  },
  {
    "text": "కల్యాణోత్సవమందు కనువిందు చేసేను\nశ్రీనివాసుడు పెండ్లికొడుకైన వేళలో\nదివ్యమంగళమయ్యె దేవదేవునికి",
    "title": "అన్నమయ్య కీర్తన 23",
    "author": "అన్నమయ్య",
    "style": "సంకీర్తన",
    "era": "15వ శతాబ్దం",
    "language": "telugu"
  },
  {
    "text": "అందమందససుందరంబుగ నంబాలిక యొప్పెన్\nచందురు డుదయించి నట్లు చందన గంధిన్\nమందార మాల్యముల్ ధరించి మందస్మితంబున\nసుందరి నడచివచ్చె చూచుచుండగ నెల్లరున్",
    "title": "భాగవత పద్యం 3",
    "author": "పోతన",
    "style": "ఉత్పలమాల",
    "era": "15వ శతాబ్దం",
    "language": "telugu"
  },
  {
    "text": "ఒక్కొక్క గుణమందు ఒప్పిన మనసుకు\nఅనుకూలమైన ఆత్మలు కలవు\nతమతమ గుణములకు తగినట్టి మిత్రులు\nచేరుచుందురయ్య సుమతీ",
    "title": "సుమతీ శతకం 14",
    "author": "బద్దెన",
    "style": "కందం",
    "era": "14వ శతాబ్దం",
    "language": "telugu"
  },
  {
    "text": "యజ్ఞ యాగాలు చేసిన యజ్ఞ పురుషుడు\nకవిత్వంలో కూడా కర్తవ్యం నిర్వర్తించెను\nభారత రచనలో భక్తిని చూపెను\nతిక్కన సోమయాజి ధర్మాత్ముడు",
    "title": "తిక్కన పద్యం 18",
    "author": "తిక్కన",
    "style": "మహాభారతం",
    "era": "13వ శతాబ్దం",
    "language": "telugu"
  },
  {
    "text": "హరినామ సంకీర్తనం హృదయశుద్ధి కలిగించు\nకరుణామయుడు కృష్ణుడు కాపాడును\nపరమపదము నొసగును పావన చరితుడు\nనరజన్మ సార్థకము నారాయణ స్మరణం",
    "title": "భాగవత పద్యం 5",
    "author": "పోతన",
    "style": "ఉత్పలమాల",
    "era": "15వ శతాబ్దం",
    "language": "telugu"
  },
  {
    "text": "సత్యమే పునాది సకల కార్యములకు\nఅసత్యము చెప్పిన అపకీర్తి వచ్చు\nసత్యవంతుడెప్పుడు సాఫల్యమందును\nవిశ్వదాభిరామ వినురవేమ",
    "title": "వేమన పద్యం 38",
    "author": "వేమన",
    "style": "ఆట వెలది",
    "era": "18వ శతాబ్దం",
    "language": "telugu"
  },
  {
    "text": "శాంతి కోసం ప్రయత్నించండి\nహింస వదలండి\nప్రేమతో బ్రతకండి\nసహనం నేర్చుకోండి",
    "title": "ఆధునిక కవిత 35",
    "author": "ఆధునిక కవి",
    "style": "వచన కవిత",
    "era": "21వ శతాబ్దం",
    "language": "telugu"
  },
  {
    "text": "ఆత్మశుద్ధి లేని యాచారమదియేల\nభాండశుద్ధి లేని పాకమేల\nచిత్తశుద్ధి లేని శివపూజలేలరా\nవిశ్వదాభిరామ వినురవేమ",
    "title": "వేమన పద్యం 3",
    "author": "వేమన",
    "style": "ఆట వెలది",
    "era": "18వ శతాబ్దం",
    "language": "telugu"
  },
  {
    "text": "మాట తప్పకు మర్యాద పాటించు\nవాగ్దానం చేసిన వదలకు",
    "title": "నీతి పద్యం 17",
    "author": "సంప్రదాయ",
    "style": "నీతి శతకం",
    "era": "సంప్రదాయ",
    "language": "telugu"
  },
  {
    "text": "ద్రౌపది వస్త్రాపహరణం\nదీనమైన స్థితిలో\nకృష్ణుడు కాపాడిన వృత్తాంతం\nకరుణ రసంతో చెప్పెను",
    "title": "నన్నయ పద్యం 19",
    "author": "నన్నయ",
    "style": "మహాభారతం",
    "era": "11వ శతాబ్దం",
    "language": "telugu"
  },
  {
    "text": "సూర్యుడు అందరికీ వెలుగునిస్తాడు\nచంద్రుడు అందరికీ చల్లదనమిస్తాడు\nసజ్జనుడు అందరికీ మేలు చేస్తాడు\nఇదే ఉదారగుణం",
    "title": "భర్తృహరి సుభాషితం 26",
    "author": "భర్తృహరి",
    "style": "సుభాషిత శతకం",
    "era": "ప్రాచీన",
    "language": "telugu"
  },
  {
    "text": "మంచివారి సంగతిచే మంచివాడగును\nచెడ్డవారి సంగతిచే చెడిపోవును\nబంగారు సంగతిచే భాసిల్లు ఇనుము\nవిశ్వదాభిరామ వినురవేమ",
    "title": "వేమన పద్యం 5",
    "author": "వేమన",
    "style": "ఆట వెలది",
    "era": "18వ శతాబ్దం",
    "language": "telugu"
  },
  {
    "text": "నిజము దప్పకుండ నీతి తప్పకుండ\nసరము దప్పకుండ సత్యమందు\nఒజ్జబంతి వలెను నొప్పుకోరి\nవిశ్వదాభిరామ వినురవేమ",
    "title": "వేమన పద్యం 8",
    "author": "వేమన",
    "style": "ఆట వెలది",
    "era": "18వ శతాబ్దం",
    "language": "telugu"
  },
  {
    "text": "గయోపాఖ్యానం నవలలో\nపురాణ కథను పునః సృష్టించెను\nభక్తి భావాలను భాసిల్లజేసెను\nచిలకమర్తి రచనా వైభవం",
    "title": "చిలకమర్తి రచన 12",
    "author": "చిలకమర్తి",
    "style": "హాస్య కవిత్వం",
    "era": "20వ శతాబ్దం",
    "language": "telugu"
  },
  {
    "text": "గురజాడ దర్శనం\nసాంఘిక మార్పు దిశగా\nకవిత్వం సాధనంగా\nసమాజ సేవకై",
    "title": "గురజాడ కవిత 12",
    "author": "గురజాడ అప్పారావు",
    "style": "సామాజిక కవిత్వం",
    "era": "20వ శతాబ్దం",
    "language": "telugu"
  },
  {
    "text": "స్నేహం అనే పూల తోట\nమిత్రులు పూలు వంటివారు\nప్రతి పువ్వు విలువైనది\nస్నేహం జీవితం",
    "title": "ఆధునిక కవిత 19",
    "author": "ఆధునిక కవి",
    "style": "వచన కవిత",
    "era": "21వ శతాబ్దం",
    "language": "telugu"
  },
  {
    "text": "కప్పలు తమ బిడ్డలు కప్పలే అని తలచు\nకోడి తన బిడ్డలకు కుంచము వేయు\nమేడల మీద మేడలు తామే అని తలచు\nపేడలు తీయని పేడలు సుమతీ",
    "title": "సుమతీ శతకం 6",
    "author": "బద్దెన",
    "style": "కందం",
    "era": "14వ శతాబ్దం",
    "language": "telugu"
  },
  {
    "text": "భారత యుద్ధమందు భగవంతుని పాత్ర\nగీతోపదేశమిచ్చి గెలిపించెను\nధర్మరాజుకు తోడుగా ధర్మము నిలబెట్టెను\nపాండవుల మిత్రుడు పరమాత్ముడు",
    "title": "భాగవత పద్యం 19",
    "author": "పోతన",
    "style": "ఉత్పలమాల",
    "era": "15వ శతాబ్దం",
    "language": "telugu"
  },
  {
    "text": "స్వాతంత్ర్య ఉద్యమంలో\nసాహిత్యం సాధనం చేసెను\nజాతీయ భావాలను జాగృతం చేసెను\nచిలకమర్తి దేశభక్తి",
    "title": "చిలకమర్తి రచన 14",
    "author": "చిలకమర్తి",
    "style": "హాస్య కవిత్వం",
    "era": "20వ శతాబ్దం",
    "language": "telugu"
  },
  {
    "text": "భాషా సంస్కరణలో భాగం\nసాహిత్య సంస్కరణలో సారం\nగురజాడ సేవలు\nగొప్పవై నిలిచాయి",
    "title": "గురజాడ కవిత 24",
    "author": "గురజాడ అప్పారావు",
    "style": "సామాజిక కవిత్వం",
    "era": "20వ శతాబ్దం",
    "language": "telugu"
  },
  {
    "text": "విరాట పర్వంలో\nపాండవుల అజ్ఞాతవాసం\nఉత్తర గోగ్రహణం\nఅర్జునుని విజయం",
    "title": "తిక్కన పద్యం 6",
    "author": "తిక్కన",
    "style": "మహాభారతం",
    "era": "13వ శతాబ్దం",
    "language": "telugu"
  },
  {
    "text": "పర్యావరణం కాపాడు ప్రకృతిని ప్రేమించు\nచెట్లు నాటు చేతనైనంత",
    "title": "నీతి పద్యం 27",
    "author": "సంప్రదాయ",
    "style": "నీతి శతకం",
    "era": "సంప్రదాయ",
    "language": "telugu"
  },
  {
    "text": "ఆరోగ్యం కాపాడుకో అన్నింటికంటే మిన్న\nఆరోగ్యమే మహాభాగ్యం",
    "title": "నీతి పద్యం 26",
    "author": "సంప్రదాయ",
    "style": "నీతి శతకం",
    "era": "సంప్రదాయ",
    "language": "telugu"
  },
  {
    "text": "పాండవులు అరణ్యవాసం\nద్రౌపది వనవాస కష్టాలు\nధర్మరాజు సహనశీలం\nతిక్కన రచనలో తేటగా కనబడు",
    "title": "తిక్కన పద్యం 23",
    "author": "తిక్కన",
    "style": "మహాభారతం",
    "era": "13వ శతాబ్దం",
    "language": "telugu"
  },
  {
    "text": "గాంధారి శాపం\nకృష్ణునికి తగిలిన శాపం\nయాదవుల అంతం\nతిక్కన కావ్యంలో తెలియజేసెను",
    "title": "తిక్కన పద్యం 24",
    "author": "తిక్కన",
    "style": "మహాభారతం",
    "era": "13వ శతాబ్దం",
    "language": "telugu"
  },
  {
    "text": "మహిళా శక్తి\nసమాజ మార్పు\nసమానత్వం కావాలి\nగౌరవం ఇవ్వండి",
    "title": "ఆధునిక కవిత 26",
    "author": "ఆధునిక కవి",
    "style": "వచన కవిత",
    "era": "21వ శతాబ్దం",
    "language": "telugu"
  },
  {
    "text": "శ్రీనాధుని కవితా శైలి\nసుందరమైన పద్యాలు\nభాషా సౌందర్యం\nకవితా మాధుర్యం",
    "title": "శ్రీనాథ పద్యం 1",
    "author": "శ్రీనాథుడు",
    "style": "ప్రబంధం",
    "era": "15వ శతాబ్దం",
    "language": "telugu"
  },
  {
    "text": "రామ నీ సమానమెవ్వరు\nలోకములో రామా\nధర్మ మూర్తివి నీవే\nకరుణా సాగరుడవు",
    "title": "త్యాగరాజ కీర్తన 10",
    "author": "త్యాగరాజు",
    "style": "కర్ణాటక సంగీతం",
    "era": "18వ శతాబ్దం",
    "language": "telugu"
  },
  {
    "text": "గురువు మాట వినాలి\nగురువు చెప్పినట్టు నడవాలి\nగురువు లేకుండా విద్య లేదు\nగురు వందనం ముఖ్యం",
    "title": "భర్తృహరి సుభాషితం 18",
    "author": "భర్తృహరి",
    "style": "సుభాషిత శతకం",
    "era": "ప్రాచీన",
    "language": "telugu"
  },
  {
    "text": "వర్షం కురిసింది\nభూమి తడిసింది\nపంటలు మొలిచినవి\nరైతు సంతోషం",
    "title": "కృష్ణశాస్త్రి కవిత 8",
    "author": "దేవులపల్లి కృష్ణశాస్త్రి",
    "style": "భావ కవిత్వం",
    "era": "20వ శతాబ్దం",
    "language": "telugu"
  },
  {
    "text": "చదివి చదియకున్నా చదువరుల వలన\nచదువని వారెల్ల చవటలయ్య\nకొండముచ్చు లెక్క కోతికేమెరుకరా\nవిశ్వదాభిరామ వినురవేమ",
    "title": "వేమన పద్యం 12",
    "author": "వేమన",
    "style": "ఆట వెలది",
    "era": "18వ శతాబ్దం",
    "language": "telugu"
  },
  {
    "text": "తల్లిదండ్రి మాట తలగుదలగు వింటె\nబుద్ధిహీనులగుదు పుత్రులెల్ల\nగురువు మాట వినని కొడుకు గుణము వాడో\nవిశ్వదాభిరామ వినురవేమ",
    "title": "వేమన పద్యం 7",
    "author": "వేమన",
    "style": "ఆట వెలది",
    "era": "18వ శతాబ్దం",
    "language": "telugu"
  },
  {
    "text": "గోదావరి తీరాన గోపన్న\nరామాలయం కట్టించెను\nభక్తి భావంతో భద్రాచలంలో\nరాముని ప్రతిష్ఠించెను",
    "title": "రామదాసు కీర్తన 17",
    "author": "రామదాసు",
    "style": "భక్తి కీర్తన",
    "era": "17వ శతాబ్దం",
    "language": "telugu"
  },
  {
    "text": "పండితారాధ్య చరిత్ర\nశైవ సంప్రదాయం\nగురు మహిమ\nభక్తి మార్గం",
    "title": "శ్రీనాథ పద్యం 9",
    "author": "శ్రీనాథుడు",
    "style": "ప్రబంధం",
    "era": "15వ శతాబ్దం",
    "language": "telugu"
  },
  {
    "text": "ప్రహ్లాద చరిత్రము ప్రసిద్ధమైనది\nభక్తాగ్రేసరుని భావము చూపు\nహిరణ్యకశిపుని హింస తట్టుకొని\nనారాయణ నామము నమ్మి బ్రతికెను",
    "title": "భాగవత పద్యం 8",
    "author": "పోతన",
    "style": "ఉత్పలమాల",
    "era": "15వ శతాబ్దం",
    "language": "telugu"
  },
  {
    "text": "స్వాతంత్ర్య పోరాటం\nధీర యోధులు\nజాతి కోసం\nప్రాణ త్యాగం",
    "title": "చిలకమర్తి రచన 8",
    "author": "చిలకమర్తి",
    "style": "హాస్య కవిత్వం",
    "era": "20వ శతాబ్దం",
    "language": "telugu"
  },
  {
    "text": "అలమేలుమంగ అండదండగ నీకు\nఇలలోన నేము ఈ సేవకులము\nబలరాముడన్న భగవంతుడు గాని\nకులదేవతవు నీవు కొలిచేము",
    "title": "అన్నమయ్య కీర్తన 7",
    "author": "అన్నమయ్య",
    "style": "సంకీర్తన",
    "era": "15వ శతాబ్దం",
    "language": "telugu"
  },
  {
    "text": "తెలుగు రంగస్థలానికి\nతేజస్సు తెచ్చిన వ్యక్తి\nకన్యాశుల్కం నాటకం\nకళారంగంలో మైలురాయి",
    "title": "గురజాడ కవిత 20",
    "author": "గురజాడ అప్పారావు",
    "style": "సామాజిక కవిత్వం",
    "era": "20వ శతాబ్దం",
    "language": "telugu"
  },
  {
    "text": "అప్పు తెచ్చినట్టి ఆనందమొక్కటే\nతీర్చు సమయమందు తెగులు వచ్చు\nఅప్పు తీర్చలేని వాడు అణగిపోవు\nవిశ్వదాభిరామ వినురవేమ",
    "title": "వేమన పద్యం 27",
    "author": "వేమన",
    "style": "ఆట వెలది",
    "era": "18వ శతాబ్దం",
    "language": "telugu"
  },
  {
    "text": "వేంకటేశ్వర వేంకటేశ్వర\nఏడుకొండల వేంకటేశ్వర\nగోవిందా గోవిందా\nగోపాలా గోవిందా",
    "title": "అన్నమయ్య కీర్తన 8",
    "author": "అన్నమయ్య",
    "style": "సంకీర్తన",
    "era": "15వ శతాబ్దం",
    "language": "telugu"
  },
  {
    "text": "మల్లెపూల మాలై వచ్చిన\nమంచి మంచి మగువా\nజాజిపూల జడ వేసుకొని\nజాణ జాణ జారిపోవా",
    "title": "జానపద గేయం 6",
    "author": "జానపద",
    "style": "గేయం",
    "era": "సంప్రదాయ",
    "language": "telugu"
  },
  {
    "text": "పూలతోట చిత్రము పులిసింహము చిత్రము\nకొండగుహల చిత్రము కోనలు చిత్రము\nప్రకృతి సృష్టి చిత్రము బ్రహ్మకు తెలియు\nవిశ్వదాభిరామ వినురవేమ",
    "title": "వేమన పద్యం 35",
    "author": "వేమన",
    "style": "ఆట వెలది",
    "era": "18వ శతాబ్దం",
    "language": "telugu"
  },
  {
    "text": "అరిషడ్వర్గములను అణచి వేయవలయు\nమనసు స్వాధీనమున మసలవలయు",
    "title": "నీతి పద్యం 3",
    "author": "సంప్రదాయ",
    "style": "నీతి శతకం",
    "era": "సంప్రదాయ",
    "language": "telugu"
  },
  {
    "text": "వకుళమాత కుమారా వేంకటేశా\nతల్లి బిడ్డల బంధము తరించెను\nవకుళాదేవి కొడుకు వేంకటేశ్వరుడు",
    "title": "అన్నమయ్య కీర్తన 20",
    "author": "అన్నమయ్య",
    "style": "సంకీర్తన",
    "era": "15వ శతాబ్దం",
    "language": "telugu"
  },
  {
    "text": "కవిత్రయంలో\nతిక్కన అద్వితీయుడు\nతెలుగు సాహిత్య దీపం\nమహా కవి తిక్కన",
    "title": "తిక్కన పద్యం 10",
    "author": "తిక్కన",
    "style": "మహాభారతం",
    "era": "13వ శతాబ్దం",
    "language": "telugu"
  },
  {
    "text": "భాగవతము చదివిన భాగ్యమందు\nపాపములన్నీ పరిహారమందు\nమోక్షమార్గము మన ముందు కనబడు\nపోతన కవిత్వము పూజనీయము",
    "title": "భాగవత పద్యం 20",
    "author": "పోతన",
    "style": "ఉత్పలమాల",
    "era": "15వ శతాబ్దం",
    "language": "telugu"
  },
  {
    "text": "తోటలో తోకచిలక\nచెట్టమీద చిలకమ్మ\nకొమ్మ మీద కోయిలమ్మ\nపాట పాడు పంచరంగు",
    "title": "జానపద గేయం 12",
    "author": "జానపద",
    "style": "గేయం",
    "era": "సంప్రదాయ",
    "language": "telugu"
  },
  {
    "text": "కాళీయ మర్దనము కృష్ణుని లీల\nయమునా నదిలో యశోదనందనుడు\nసర్పరాజును సాధువుగా మార్చెను\nకృష్ణ మహిమ కథలు కొన్ని వేలు",
    "title": "భాగవత పద్యం 15",
    "author": "పోతన",
    "style": "ఉత్పలమాల",
    "era": "15వ శతాబ్దం",
    "language": "telugu"
  },
  {
    "text": "ఓర్పుతో ఉండు ఓటమి వచ్చినా\nప్రయత్నం మానకు పట్టుదల ఉండు",
    "title": "నీతి పద్యం 24",
    "author": "సంప్రదాయ",
    "style": "నీతి శతకం",
    "era": "సంప్రదాయ",
    "language": "telugu"
  },
  {
    "text": "పద్నాలుగో శతాబ్దపు పద్య కవి శ్రేష్ఠుడు\nకావ్యాలందు కమనీయత చూపెను\nభాషా సంపదలో భాస్కరుడాయెను\nశ్రీనాథుని కీర్తి కాలాతీతం",
    "title": "శ్రీనాథ పద్యం 24",
    "author": "శ్రీనాథుడు",
    "style": "ప్రబంధం",
    "era": "15వ శతాబ్దం",
    "language": "telugu"
  },
  {
    "text": "చందమామ రావే\nజాబిల్లి రావే\nనీ పాప వచ్చెను\nపాలాళి తెచ్చెను",
    "title": "జానపద గేయం 1",
    "author": "జానపద",
    "style": "గేయం",
    "era": "సంప్రదాయ",
    "language": "telugu"
  },
  {
    "text": "భద్రాచలం క్షేత్రంలో భక్తి సాగరంలో\nరామదాసు మునిగి తేలెను\nరామ నామ స్మరణలో రసానుభవంలో\nధన్యుడై తరించెను",
    "title": "రామదాసు కీర్తన 11",
    "author": "రామదాసు",
    "style": "భక్తి కీర్తన",
    "era": "17వ శతాబ్దం",
    "language": "telugu"
  },
  {
    "text": "వ్యాస భారతాన్ని వచన పద్యాలలో\nతెలుగు తల్లికి అర్పించెను\nమహాభారత కథలు మనకందించెను\nతిక్కన మహాకవి తేజోమూర్తి",
    "title": "తిక్కన పద్యం 13",
    "author": "తిక్కన",
    "style": "మహాభారతం",
    "era": "13వ శతాబ్దం",
    "language": "telugu"
  },
  {
    "text": "వాతాపి గణపతిం భజే\nవిఘ్న నాశక వినాయకా\nగణనాథ నమస్కారం\nసిద్ధి బుద్ధి ప్రదాతా",
    "title": "త్యాగరాజ కీర్తన 13",
    "author": "త్యాగరాజు",
    "style": "కర్ణాటక సంగీతం",
    "era": "18వ శతాబ్దం",
    "language": "telugu"
  },
  {
    "text": "సోషల్ మీడియా వేదికలో\nజాగ్రత్తగా నడుచుకో\nనకిలీలు ఎన్నో ఉన్నాయి\nనిజాలు కనుక్కో",
    "title": "ఆధునిక కవిత 38",
    "author": "ఆధునిక కవి",
    "style": "వచన కవిత",
    "era": "21వ శతాబ్దం",
    "language": "telugu"
  },
  {
    "text": "సామాజిక చైతన్యం\nకవిత్వంలో వ్యక్తం\nమార్పు కోసం పిలుపు\nసమాజ సేవ",
    "title": "చిలకమర్తి రచన 5",
    "author": "చిలకమర్తి",
    "style": "హాస్య కవిత్వం",
    "era": "20వ శతాబ్దం",
    "language": "telugu"
  },
  {
    "text": "ఆధునిక తెలుగు కవిత్వం\nఆరంభమైన చోటు\nగురజాడ రచనలతో\nగమ్యం చేరిన చోటు",
    "title": "గురజాడ కవిత 23",
    "author": "గురజాడ అప్పారావు",
    "style": "సామాజిక కవిత్వం",
    "era": "20వ శతాబ్దం",
    "language": "telugu"
  },
  {
    "text": "కాశీఖండం కావ్యం\nపుణ్య క్షేత్ర వర్ణన\nవారాణసి మహిమ\nగంగా స్నాన ఫలం",
    "title": "శ్రీనాథ పద్యం 7",
    "author": "శ్రీనాథుడు",
    "style": "ప్రబంధం",
    "era": "15వ శతాబ్దం",
    "language": "telugu"
  },
  {
    "text": "సహనం అలవాటు చేసుకో సంతోషం కలుగు\nఆగ్రహం అణచుకో ఆనందం పొందు",
    "title": "నీతి పద్యం 29",
    "author": "సంప్రదాయ",
    "style": "నీతి శతకం",
    "era": "సంప్రదాయ",
    "language": "telugu"
  },
  {
    "text": "శాంతి లేని మనసు శవము వంటిది\nక్రోధము లేని జీవితం కొండంత సుఖము\nప్రేమతో బ్రతుకు ప్రశాంతముగా\nశాంతియే స్వర్గము సుమతీ",
    "title": "సుమతీ శతకం 30",
    "author": "బద్దెన",
    "style": "కందం",
    "era": "14వ శతాబ్దం",
    "language": "telugu"
  },
  {
    "text": "శారద నివాసము చేసేను\nసరస్వతీ హృదయంలో\nజ్ఞానము ఇచ్చే తల్లి నీవే\nవిద్యాదాత్రి వందనం",
    "title": "త్యాగరాజ కీర్తన 5",
    "author": "త్యాగరాజు",
    "style": "కర్ణాటక సంగీతం",
    "era": "18వ శతాబ్దం",
    "language": "telugu"
  },
  {
    "text": "నరసింహస్వామి నా రక్షకుడు\nస్తంభమందు సాక్షాత్కరించెను\nప్రహ్లాదుని కాపాడ ప్రభువు వచ్చెను\nభక్తవత్సలుడు భగవంతుడు",
    "title": "భాగవత పద్యం 9",
    "author": "పోతన",
    "style": "ఉత్పలమాల",
    "era": "15వ శతాబ్దం",
    "language": "telugu"
  },
  {
    "text": "చిలకమర్తి లక్ష్మీనరసింహం\nతెలుగు సాహిత్య దిగ్గజం\nహాస్య రస ప్రియుడు\nవచన కవిత్వ ప్రవర్తకుడు",
    "title": "చిలకమర్తి రచన 11",
    "author": "చిలకమర్తి",
    "style": "హాస్య కవిత్వం",
    "era": "20వ శతాబ్దం",
    "language": "telugu"
  },
  {
    "text": "చెరసాల బంధనంలో\nరాముని స్మరించితిని\nత్రాళ్లు తెగిపోయినవి\nరామ కృప వల్లనే",
    "title": "రామదాసు కీర్తన 9",
    "author": "రామదాసు",
    "style": "భక్తి కీర్తన",
    "era": "17వ శతాబ్దం",
    "language": "telugu"
  },
  {
    "text": "బుద్ధిమంతుడైన బూడిదె బంగారు\nతెలివిలేనివాడు దేవుడైన\nమట్టిబొమ్మ వంటి మనుషులు వ్యర్థము\nవిశ్వదాభిరామ వినురవేమ",
    "title": "వేమన పద్యం 32",
    "author": "వేమన",
    "style": "ఆట వెలది",
    "era": "18వ శతాబ్దం",
    "language": "telugu"
  },
  {
    "text": "తెలుగు పద్యంలో తెలుగుదనం నింపెను\nకావ్య రచనలో కలం నడిపెను\nసాహిత్య సేవలో సర్వస్వం అర్పించెను\nశ్రీనాథుని సేవ శాశ్వతం",
    "title": "శ్రీనాథ పద్యం 26",
    "author": "శ్రీనాథుడు",
    "style": "ప్రబంధం",
    "era": "15వ శతాబ్దం",
    "language": "telugu"
  },
  {
    "text": "కలాన్ని కత్తిగా మార్చి\nకదలిక తెచ్చాడు\nసమాజంలో మార్పు కోసం\nసాహిత్యంలో పోరాడాడు",
    "title": "శ్రీశ్రీ కవిత 11",
    "author": "శ్రీశ్రీ",
    "style": "అభ్యుదయ కవిత్వం",
    "era": "20వ శతాబ్దం",
    "language": "telugu"
  },
  {
    "text": "ఎందరో మహానుభావులు\nఅందరికీ వందనాలు\nచందన చర్చిత నీల\nకలేబర హృదయవాసా",
    "title": "త్యాగరాజ కీర్తన 1",
    "author": "త్యాగరాజు",
    "style": "కర్ణాటక సంగీతం",
    "era": "18వ శతాబ్దం",
    "language": "telugu"
  },
  {
    "text": "అభ్యుదయ కవిత్వం\nఆధునిక తెలుగు వెలుగు\nశ్రీశ్రీ కలం\nశ్రమజీవుల కోసం",
    "title": "శ్రీశ్రీ కవిత 3",
    "author": "శ్రీశ్రీ",
    "style": "అభ్యుదయ కవిత్వం",
    "era": "20వ శతాబ్దం",
    "language": "telugu"
  },
  {
    "text": "దేశ భక్తి\nజాతి ప్రేమ\nసేవా భావం\nత్యాగ శీలం",
    "title": "చిలకమర్తి రచన 7",
    "author": "చిలకమర్తి",
    "style": "హాస్య కవిత్వం",
    "era": "20వ శతాబ్దం",
    "language": "telugu"
  },
  {
    "text": "గుర్తింపు కోసం గొడవ చేయకు\nమంచి పనులు చేస్తే మర్యాద వచ్చును",
    "title": "నీతి పద్యం 15",
    "author": "సంప్రదాయ",
    "style": "నీతి శతకం",
    "era": "సంప్రదాయ",
    "language": "telugu"
  },
  {
    "text": "వినయమందు గొప్ప విజయాలు వచ్చును\nగర్వమందు చెడు కష్టాలు వచ్చు\nతల వంచి నడచిన తప్పులుండవయా\nవినయమే విజయము సుమతీ",
    "title": "సుమతీ శతకం 29",
    "author": "బద్దెన",
    "style": "కందం",
    "era": "14వ శతాబ్దం",
    "language": "telugu"
  },
  {
    "text": "పల్లె సీమల అందాలు\nపంట పొలాల పరిమళం\nకృష్ణశాస్త్రి కవితలలో\nకమనీయంగా చూపెను",
    "title": "కృష్ణశాస్త్రి కవిత 16",
    "author": "దేవులపల్లి కృష్ణశాస్త్రి",
    "style": "భావ కవిత్వం",
    "era": "20వ శతాబ్దం",
    "language": "telugu"
  },
  {
    "text": "తెలుగు కవిత్వాన్ని తేజోవంతం చేసిన\nదేవులపల్లి కృష్ణశాస్త్రి\nప్రకృతి వర్ణనలో ప్రథముడు\nభావ కవిత్వంలో భూషణం",
    "title": "కృష్ణశాస్త్రి కవిత 24",
    "author": "దేవులపల్లి కృష్ణశాస్త్రి",
    "style": "భావ కవిత్వం",
    "era": "20వ శతాబ్దం",
    "language": "telugu"
  },
  {
    "text": "అలరులు గురియగా\nపూలవానలు పొలియగా\nమాలలు మాలలు గట్టి\nపాలించెదము దేవా నిన్ను",
    "title": "అన్నమయ్య కీర్తన 3",
    "author": "అన్నమయ్య",
    "style": "సంకీర్తన",
    "era": "15వ శతాబ్దం",
    "language": "telugu"
  },
  {
    "text": "సంస్కృత భారతాన్ని తెలుగులో\nసరళంగా అనువదించెను\nతెలుగు భాష మాధుర్యం\nతేనెలా తీపిగా చూపెను",
    "title": "నన్నయ పద్యం 5",
    "author": "నన్నయ",
    "style": "మహాభారతం",
    "era": "11వ శతాబ్దం",
    "language": "telugu"
  },
  {
    "text": "కమ్మరి కొలిమిలో కరిగేను ఇనుము\nకర్రెడ్లు బసవల్లు కష్టజీవులు\nలోహ వస్తువులు లోకానికి ఇచ్చేరు",
    "title": "జానపద గేయం 26",
    "author": "జానపద",
    "style": "గేయం",
    "era": "సంప్రదాయ",
    "language": "telugu"
  },
  {
    "text": "క్షమ ఉన్నవాడికి కవచం అవసరం లేదు\nశాంతి ఉన్నవాడికి శత్రువులు లేరు\nజ్ఞానం ఉన్నవాడికి జరా మరణం లేవు\nభర్తృహరి మహావాక్యం",
    "title": "భర్తృహరి సుభాషితం 6",
    "author": "భర్తృహరి",
    "style": "సుభాషిత శతకం",
    "era": "ప్రాచీన",
    "language": "telugu"
  },
  {
    "text": "ఆధునిక తెలుగు సాహిత్యానికి\nఆద్యుడు గురజాడ అప్పారావు\nగద్య పద్య నాటకాలలో\nగొప్ప రచయిత",
    "title": "గురజాడ కవిత 15",
    "author": "గురజాడ అప్పారావు",
    "style": "సామాజిక కవిత్వం",
    "era": "20వ శతాబ్దం",
    "language": "telugu"
  },
  {
    "text": "జో అచ్యుతానంద జో జో ముకుందా\nలాలనుచు నీతల్లి నిను బిలిచే నందా\nజో అచ్యుతానంద జో జో ముకుందా",
    "title": "జానపద గేయం 2",
    "author": "జానపద",
    "style": "గేయం",
    "era": "సంప్రదాయ",
    "language": "telugu"
  },
  {
    "text": "పత్రికా రచయితగా పనిచేసెను\nసామాజిక సమస్యలపై సంధించెను\nకలం సాధనంగా కదలిక తెచ్చెను\nచిలకమర్తి సేవ సమాజానికి",
    "title": "చిలకమర్తి రచన 19",
    "author": "చిలకమర్తి",
    "style": "హాస్య కవిత్వం",
    "era": "20వ శతాబ్దం",
    "language": "telugu"
  },
  {
    "text": "తెలుగు వెలుగు నా తెలుగు భాష\nతేనె వంటి మాధుర్యం\nతల్లి భాష నా తెలుగు భాష\nతరతరాలుగా మా వారసత్వం",
    "title": "ఆధునిక కవిత 1",
    "author": "ఆధునిక కవి",
    "style": "వచన కవిత",
    "era": "21వ శతాబ్దం",
    "language": "telugu"
  },
  {
    "text": "ధర్మరాజు రాజ్యాభిషేకం\nధర్మం గెలిచిన వేళలో\nపాండవులు జయించిన యుద్ధంలో\nతిక్కన కావ్యంలో తేటగా చూపెను",
    "title": "తిక్కన పద్యం 20",
    "author": "తిక్కన",
    "style": "మహాభారతం",
    "era": "13వ శతాబ్దం",
    "language": "telugu"
  },
  {
    "text": "కొత్త వారితోడ కొంత సంకోచముండు\nపాత వారితోడ ప్రాణమీయు\nస్నేహమంత గొప్ప సుగుణాల మూటరా\nవిశ్వదాభిరామ వినురవేమ",
    "title": "వేమన పద్యం 39",
    "author": "వేమన",
    "style": "ఆట వెలది",
    "era": "18వ శతాబ్దం",
    "language": "telugu"
  },
  {
    "text": "ప్రకృతి సౌందర్యం పద్యాలలో\nకృష్ణశాస్త్రి కవిత్వంలో\nతెలుగు పదాల తేనెలో\nమధురమైన రసానుభవం",
    "title": "కృష్ణశాస్త్రి కవిత 12",
    "author": "దేవులపల్లి కృష్ణశాస్త్రి",
    "style": "భావ కవిత్వం",
    "era": "20వ శతాబ్దం",
    "language": "telugu"
  },
  {
    "text": "శేషాద్రికొండపై వెలసిన స్వామి\nఆదిశేషుడు నీకు ఆధారమయ్య\nశేషవాహన దేవా శ్రీనివాసా",
    "title": "అన్నమయ్య కీర్తన 16",
    "author": "అన్నమయ్య",
    "style": "సంకీర్తన",
    "era": "15వ శతాబ్దం",
    "language": "telugu"
  },
  {
    "text": "ద్రౌపది స్వయంవరం\nదివ్యమైన ఘట్టం\nపాండవుల కథలు\nపద్యాలలో వెలిసెను",
    "title": "నన్నయ పద్యం 9",
    "author": "నన్నయ",
    "style": "మహాభారతం",
    "era": "11వ శతాబ్దం",
    "language": "telugu"
  },
  {
    "text": "ఆలియైన అత్తయైన అన్నదమ్ములైన\nకలిమిలేమి బట్టి కక్కుర్తి పడును\nదరిద్రునకు బంధువులు దాటిపోవురా సుమతీ",
    "title": "సుమతీ శతకం 11",
    "author": "బద్దెన",
    "style": "కందం",
    "era": "14వ శతాబ్దం",
    "language": "telugu"
  },
  {
    "text": "మహాభారత కథలో\nమాధుర్యం నింపెను\nధర్మాధర్మ విచారణలో\nధర్మ పక్షం చూపెను",
    "title": "నన్నయ పద్యం 17",
    "author": "నన్నయ",
    "style": "మహాభారతం",
    "era": "11వ శతాబ్దం",
    "language": "telugu"
  },
  {
    "text": "తెలుగు సాహిత్య చరిత్రలో\nతేజోమూర్తిగా నిలిచెను\nగురజాడ అప్పారావు\nగొప్ప రచయిత అయ్యెను",
    "title": "గురజాడ కవిత 25",
    "author": "గురజాడ అప్పారావు",
    "style": "సామాజిక కవిత్వం",
    "era": "20వ శతాబ్దం",
    "language": "telugu"
  },
  {
    "text": "తెలుగు వారి\nసాహిత్య సంపద\nచిలకమర్తి రచనలు\nతరతరాలుగా నిలిచు",
    "title": "చిలకమర్తి రచన 4",
    "author": "చిలకమర్తి",
    "style": "హాస్య కవిత్వం",
    "era": "20వ శతాబ్దం",
    "language": "telugu"
  },
  {
    "text": "ఆదికవి నన్నయ భట్టు\nఆంధ్ర భాష వెలిగించెను\nమహాభారతం తెలుగులో\nమొదటిసారిగా రచించెను",
    "title": "నన్నయ పద్యం 1",
    "author": "నన్నయ",
    "style": "మహాభారతం",
    "era": "11వ శతాబ్దం",
    "language": "telugu"
  },
  {
    "text": "రాజు తప్పు చేసిన రాజ్యము చెడిపోవు\nప్రజ తప్పు చేసిన పాలన చెడు\nఇద్దరు మంచిగ యుంటె ఇహలోక స్వర్గము\nమంచితనమే ధర్మము సుమతీ",
    "title": "సుమతీ శతకం 27",
    "author": "బద్దెన",
    "style": "కందం",
    "era": "14వ శతాబ్దం",
    "language": "telugu"
  },
  {
    "text": "కోపం వచ్చినప్పుడు కొంచెం ఆగు\nమాట్లాడే ముందు ఆలోచించు\nచెప్పాక చేయలేవు అదే తప్పు\nభర్తృహరి నీతి పద్యం",
    "title": "భర్తృహరి సుభాషితం 11",
    "author": "భర్తృహరి",
    "style": "సుభాషిత శతకం",
    "era": "ప్రాచీన",
    "language": "telugu"
  },
  {
    "text": "నాటక రంగంలో నవ్య ప్రయోగాలు\nకథా రచనలో కమనీయ శైలి\nచిలకమర్తి సాహిత్యం\nచిరస్మరణీయం",
    "title": "చిలకమర్తి రచన 17",
    "author": "చిలకమర్తి",
    "style": "హాస్య కవిత్వం",
    "era": "20వ శతాబ్దం",
    "language": "telugu"
  },
  {
    "text": "అమ్మ ప్రేమ అమూల్యం\nనాన్న త్యాగం మహత్తరం\nకుటుంబ బంధం గొప్ప\nప్రేమలో ఆనందం",
    "title": "ఆధునిక కవిత 18",
    "author": "ఆధునిక కవి",
    "style": "వచన కవిత",
    "era": "21వ శతాబ్దం",
    "language": "telugu"
  },
  {
    "text": "ఆలి దూరముండి అత్తకే మగువలు\nతల్లి దూరముండి దనుకు మగువ\nచల్లకావి సంగతి చల్ల కష్టమురా\nవిశ్వదాభిరామ వినురవేమ",
    "title": "వేమన పద్యం 11",
    "author": "వేమన",
    "style": "ఆట వెలది",
    "era": "18వ శతాబ్దం",
    "language": "telugu"
  },
  {
    "text": "సత్యమే జయం సదా గెలుచును\nధర్మము నిలిచేను ధర్మమూర్తిగా",
    "title": "నీతి పద్యం 4",
    "author": "సంప్రదాయ",
    "style": "నీతి శతకం",
    "era": "సంప్రదాయ",
    "language": "telugu"
  },
  {
    "text": "వినయమందు గొప్ప విజయాలు వచ్చును\nగర్వమందు చెడు కష్టాలు వచ్చు\nతలవంచి నడచిన తప్పులుండవయా\nవిశ్వదాభిరామ వినురవేమ",
    "title": "వేమన పద్యం 31",
    "author": "వేమన",
    "style": "ఆట వెలది",
    "era": "18వ శతాబ్దం",
    "language": "telugu"
  },
  {
    "text": "బూటకాలను బట్టబయలు చేసాడు\nమోసాలను మొత్తుకున్నాడు\nప్రజా పక్షం వహించి\nపోరాట కవిగా నిలిచాడు",
    "title": "శ్రీశ్రీ కవిత 15",
    "author": "శ్రీశ్రీ",
    "style": "అభ్యుదయ కవిత్వం",
    "era": "20వ శతాబ్దం",
    "language": "telugu"
  },
  {
    "text": "ప్రజాస్వామ్యం గొప్ప\nస్వేచ్ఛ హక్కు\nబాధ్యతలు నిర్వర్తించండి\nమంచి పౌరులు అవ్వండి",
    "title": "ఆధునిక కవిత 34",
    "author": "ఆధునిక కవి",
    "style": "వచన కవిత",
    "era": "21వ శతాబ్దం",
    "language": "telugu"
  },
  {
    "text": "భాగవత దశమ స్కంధం\nకృష్ణ లీలలు\nభక్తి రసం\nదివ్య కథనం",
    "title": "శ్రీనాథ పద్యం 14",
    "author": "శ్రీనాథుడు",
    "style": "ప్రబంధం",
    "era": "15వ శతాబ్దం",
    "language": "telugu"
  },
  {
    "text": "కాలం మారినా కవిత్వం నిలిచింది\nశతాబ్దాలు గడిచినా శైలి గుర్తుండింది\nతరతరాలుగా తరించింది తెలుగు\nశ్రీనాథుని సాహిత్యం శాశ్వతం",
    "title": "శ్రీనాథ పద్యం 28",
    "author": "శ్రీనాథుడు",
    "style": "ప్రబంధం",
    "era": "15వ శతాబ్దం",
    "language": "telugu"
  },
  {
    "text": "భర్తృహరి సుభాషితాలు\nభారతీయ జ్ఞానసంపద\nనీతి పద్యాలలో నిధులు\nతెలుగులో తేజస్సు",
    "title": "భర్తృహరి సుభాషితం 30",
    "author": "భర్తృహరి",
    "style": "సుభాషిత శతకం",
    "era": "ప్రాచీన",
    "language": "telugu"
  },
  {
    "text": "ఇంటి ఇంటి లోన ఇల్లాలు పెద్దను\nఊరి ఊరికెల్ల ఊరపెద్ద\nరాజు రాజ్యమంత రాజే పెద్దరా\nవిశ్వదాభిరామ వినురవేమ",
    "title": "వేమన పద్యం 21",
    "author": "వేమన",
    "style": "ఆట వెలది",
    "era": "18వ శతాబ్దం",
    "language": "telugu"
  },
  {
    "text": "గోవిందా గోవిందా గోపాల గోవిందా\nమాధవా మాధవా మానస పద్మ\nకేశవా కేశవా క్లేశనాశన\nనారాయణా నారాయణా నమో నమః",
    "title": "భాగవత పద్యం 6",
    "author": "పోతన",
    "style": "ఉత్పలమాల",
    "era": "15వ శతాబ్దం",
    "language": "telugu"
  },
  {
    "text": "పక్షి రెక్కలు లేకపోయినా కల\nచేప నీళ్లు లేకపోయినా తన\nమనిషి మనసు లేకపోయినా ఏమి\nప్రేమ లేని జీవితం శూన్యం",
    "title": "ఆధునిక కవిత 7",
    "author": "ఆధునిక కవి",
    "style": "వచన కవిత",
    "era": "21వ శతాబ్దం",
    "language": "telugu"
  },
  {
    "text": "మూఢ నమ్మకాలు వదలండి\nశాస్త్రం నేర్చుకోండి\nహేతువాదం అవసరం\nపురోగతి సాధించండి",
    "title": "గురజాడ కవిత 8",
    "author": "గురజాడ అప్పారావు",
    "style": "సామాజిక కవిత్వం",
    "era": "20వ శతాబ్దం",
    "language": "telugu"
  },
  {
    "text": "తిరువయ్యూరులో తేజోమూర్తి\nరామ భక్తిలో రసజ్ఞుడు\nసంగీత లోకంలో సార్వభౌముడు\nత్యాగరాజ స్వామి వందనం",
    "title": "త్యాగరాజ కీర్తన 24",
    "author": "త్యాగరాజు",
    "style": "కర్ణాటక సంగీతం",
    "era": "18వ శతాబ్దం",
    "language": "telugu"
  },
  {
    "text": "పద్మవ్యూహంలో అభిమన్యుడు\nకర్ణార్జున యుద్ధం కదన రంగంలో\nభీమ దుశ్శాసన భీకర పోరాటం\nతిక్కన కవిత్వంలో తేజస్సుగా వెలిగెను",
    "title": "తిక్కన పద్యం 19",
    "author": "తిక్కన",
    "style": "మహాభారతం",
    "era": "13వ శతాబ్దం",
    "language": "telugu"
  },
  {
    "text": "తెలుగు భాష మధురం\nతెలుగు పదం సుందరం\nతెలుగు వెలుగు చల్లర్చు\nతెలుగు జాతి వర్ధిల్లు",
    "title": "గురజాడ కవిత 11",
    "author": "గురజాడ అప్పారావు",
    "style": "సామాజిక కవిత్వం",
    "era": "20వ శతాబ్దం",
    "language": "telugu"
  },
  {
    "text": "నీటి బొట్టు రాయి తొలిచును\nమాట మంచి మనసు గెలిచును\nప్రయత్నం పరమ సాధనం\nవిజయం వచ్చేను చివరికి",
    "title": "ఆధునిక కవిత 5",
    "author": "ఆధునిక కవి",
    "style": "వచన కవిత",
    "era": "21వ శతాబ్దం",
    "language": "telugu"
  },
  {
    "text": "పాము విషం దంతంలో ఉంటుంది\nతేలు విషం తోకలో ఉంటుంది\nదుష్టుని విషం ఎక్కడ ఉంటుందో తెలియదు\nజాగ్రత్తగా ఉండాలి",
    "title": "భర్తృహరి సుభాషితం 27",
    "author": "భర్తృహరి",
    "style": "సుభాషిత శతకం",
    "era": "ప్రాచీన",
    "language": "telugu"
  },
  {
    "text": "సముద్రం అలల సంగీతం\nగాలి వాయువుల వీణ\nమేఘాల మెరుపుల తాళం\nప్రకృతి ఆర్కెస్ట్రా అద్భుతం",
    "title": "ఆధునిక కవిత 12",
    "author": "ఆధునిక కవి",
    "style": "వచన కవిత",
    "era": "21వ శతాబ్దం",
    "language": "telugu"
  },
  {
    "text": "అశ్వమేధ పర్వం\nధర్మరాజు యాగం\nరాజ్య స్థాపన\nధర్మ పరిపాలన",
    "title": "తిక్కన పద్యం 9",
    "author": "తిక్కన",
    "style": "మహాభారతం",
    "era": "13వ శతాబ్దం",
    "language": "telugu"
  },
  {
    "text": "విజయనగర సామ్రాజ్యంలో వెలిగెను\nరాయల ఆస్థానంలో రాజమర్యాద\nకవులకు గురువుగా కనబడెను\nశ్రీనాథుని యశస్సు శాశ్వతం",
    "title": "శ్రీనాథ పద్యం 19",
    "author": "శ్రీనాథుడు",
    "style": "ప్రబంధం",
    "era": "15వ శతాబ్దం",
    "language": "telugu"
  },
  {
    "text": "నిధి చాలా సుఖమా\nరామ భక్తి సుఖమా\nధనము కంటే భక్తి మిన్న\nరామ నామ స్మరణ సుఖం",
    "title": "త్యాగరాజ కీర్తన 2",
    "author": "త్యాగరాజు",
    "style": "కర్ణాటక సంగీతం",
    "era": "18వ శతాబ్దం",
    "language": "telugu"
  },
  {
    "text": "విద్య ఉన్నవాడికి విదేశం లేదు\nఎక్కడికి వెళ్ళినా గౌరవం పొందుతాడు\nసింహం అడవిలో అడుగు పెట్టినంతనే\nసకల మృగాలు భయపడతాయి",
    "title": "భర్తృహరి సుభాషితం 4",
    "author": "భర్తృహరి",
    "style": "సుభాషిత శతకం",
    "era": "ప్రాచీన",
    "language": "telugu"
  },
  {
    "text": "నేర్పు లేని వాడు నేర్పు గలవాని\nకొలువు చేసి బ్రతుకు గొప్పగాను\nతెల్లవారి రాత్రి తెల్లముగ బ్రతుకు\nవిశ్వదాభిరామ వినురవేమ",
    "title": "వేమన పద్యం 15",
    "author": "వేమన",
    "style": "ఆట వెలది",
    "era": "18వ శతాబ్దం",
    "language": "telugu"
  },
  {
    "text": "కడు చిన్నవాడైన కార్య దీర్చగలడు\nపెద్దవాడైనను పెద్దలెందరు చేరియు\nచేయలేని కార్యము చిన్నవాడు చేయు\nచేవ ముఖ్యమయ్య సుమతీ",
    "title": "సుమతీ శతకం 16",
    "author": "బద్దెన",
    "style": "కందం",
    "era": "14వ శతాబ్దం",
    "language": "telugu"
  },
  {
    "text": "చూడర సంసారము సుఖమైన సంసారము\nచూడర సంసారము సుఖమైన సంసారము\nఈడేరనివాని సంసారము ఎంత సుఖము\nకాడికి రాదది కష్టమైన సంసారము",
    "title": "అన్నమయ్య కీర్తన 6",
    "author": "అన్నమయ్య",
    "style": "సంకీర్తన",
    "era": "15వ శతాబ్దం",
    "language": "telugu"
  },
  {
    "text": "శ్రమించడం నేర్చుకో శ్రేయస్సు కలుగు\nసోమరితనం సర్వనాశనం",
    "title": "నీతి పద్యం 12",
    "author": "సంప్రదాయ",
    "style": "నీతి శతకం",
    "era": "సంప్రదాయ",
    "language": "telugu"
  },
  {
    "text": "పుస్తకాలు చదువు పూర్తిగా నేర్చుకో\nచదివినంత కాదు చర్చించవలయు\nజ్ఞానమందు గొప్ప జన్మకు ప్రయోజనము\nవిశ్వదాభిరామ వినురవేమ",
    "title": "వేమన పద్యం 40",
    "author": "వేమన",
    "style": "ఆట వెలది",
    "era": "18వ శతాబ్దం",
    "language": "telugu"
  },
  {
    "text": "సైన్స్ అభివృద్ధి\nశాస్త్ర పురోగతి\nపరిశోధన అవసరం\nఆవిష్కరణలు చేయండి",
    "title": "ఆధునిక కవిత 31",
    "author": "ఆధునిక కవి",
    "style": "వచన కవిత",
    "era": "21వ శతాబ్దం",
    "language": "telugu"
  },
  {
    "text": "సంస్కృతాంధ్ర భాషలలో\nసమర్థత చూపెను\nద్విభాషా పండితుడుగా\nదివ్యమైన రచన చేసెను",
    "title": "నన్నయ పద్యం 12",
    "author": "నన్నయ",
    "style": "మహాభారతం",
    "era": "11వ శతాబ్దం",
    "language": "telugu"
  },
  {
    "text": "పరుల సాయం పరమార్థం\nస్వార్థం లేని సేవ శ్రేష్ఠం",
    "title": "నీతి పద్యం 8",
    "author": "సంప్రదాయ",
    "style": "నీతి శతకం",
    "era": "సంప్రదాయ",
    "language": "telugu"
  },
  {
    "text": "సామాజిక సమస్యలను సాహిత్యంలో\nహాస్యంగా హ్రాదయానికి హత్తించెను\nమార్పు కావాలని మనసులో నాటెను\nచిలకమర్తి సామాజిక సేవ",
    "title": "చిలకమర్తి రచన 16",
    "author": "చిలకమర్తి",
    "style": "హాస్య కవిత్వం",
    "era": "20వ శతాబ్దం",
    "language": "telugu"
  },
  {
    "text": "ధనం వల్ల దురహంకారం వస్తుంది\nయౌవనం వల్ల మదం వస్తుంది\nఈ రెండూ కలిస్తే అవివేకం వస్తుంది\nభర్తృహరి హెచ్చరిక",
    "title": "భర్తృహరి సుభాషితం 5",
    "author": "భర్తృహరి",
    "style": "సుభాషిత శతకం",
    "era": "ప్రాచీన",
    "language": "telugu"
  },
  {
    "text": "లోభి ధనము దాచి లోకంలో చెడిపోవు\nదాని వాడు దానధర్మము చేయు\nధనము ఉపయోగించు ధన్యుడవును\nదానమే ధర్మము సుమతీ",
    "title": "సుమతీ శతకం 28",
    "author": "బద్దెన",
    "style": "కందం",
    "era": "14వ శతాబ్దం",
    "language": "telugu"
  },
  {
    "text": "ఎర్ర ఎర్ర ఎర్ర రోజా\nపచ్చ పచ్చ పచ్చ రంగు\nతెల్ల తెల్ల తెల్ల మల్లె\nనల్ల నల్ల నల్ల కన్ను",
    "title": "జానపద గేయం 5",
    "author": "జానపద",
    "style": "గేయం",
    "era": "సంప్రదాయ",
    "language": "telugu"
  },
  {
    "text": "తెలుగునాట భక్తి సాంప్రదాయంలో\nరామదాసు కీర్తనలు ప్రసిద్ధం\nరామ నామ స్మరణలో రసజ్ఞత\nరామదాసు భక్తి మార్గం",
    "title": "రామదాసు కీర్తన 20",
    "author": "రామదాసు",
    "style": "భక్తి కీర్తన",
    "era": "17వ శతాబ్దం",
    "language": "telugu"
  },
  {
    "text": "లాలి లాలి లాలి లాలమ్మ\nలాలి లాలనుచు తల్లి పాడెను\nబంగారు బొమ్మ నా బంగారు బొమ్మ\nబంగారు తల్లి నా పంచప్రాణాలు",
    "title": "జానపద గేయం 3",
    "author": "జానపద",
    "style": "గేయం",
    "era": "సంప్రదాయ",
    "language": "telugu"
  },
  {
    "text": "సంస్కృతి సంప్రదాయం\nరక్షించాలి పెంచాలి\nఆధునికత స్వీకరించండి\nమూలాలు మరవకండి",
    "title": "ఆధునిక కవిత 33",
    "author": "ఆధునిక కవి",
    "style": "వచన కవిత",
    "era": "21వ శతాబ్దం",
    "language": "telugu"
  },
  {
    "text": "కుటుంబ బాధ్యత కొంచెము కాదు\nకలిసి ఉంటే కళ్యాణమే",
    "title": "నీతి పద్యం 19",
    "author": "సంప్రదాయ",
    "style": "నీతి శతకం",
    "era": "సంప్రదాయ",
    "language": "telugu"
  },
  {
    "text": "సంగీత త్రిమూర్తులలో\nసరస్వతీ పుత్రుడు త్యాగరాజు\nరామ భక్తిలో రాగాలలో\nరమ్యంగా పాడెను",
    "title": "త్యాగరాజ కీర్తన 21",
    "author": "త్యాగరాజు",
    "style": "కర్ణాటక సంగీతం",
    "era": "18వ శతాబ్దం",
    "language": "telugu"
  },
  {
    "text": "విమర్శకులు మెచ్చిన విద్వత్ కవిత్వం\nపండితులు పొగడిన పద్య రచనలు\nసామాన్యులు ఆనందించిన సాహిత్యం\nశ్రీనాథుడు అందరికీ ఆదర్శం",
    "title": "శ్రీనాథ పద్యం 27",
    "author": "శ్రీనాథుడు",
    "style": "ప్రబంధం",
    "era": "15వ శతాబ్దం",
    "language": "telugu"
  },
  {
    "text": "కులం మతం వదలిపెట్టి\nమానవత్వం పెంచుకోండి\nఐక్యతలో శక్తి ఉంది\nకలిసి నడిస్తే జయం వచ్చు",
    "title": "గురజాడ కవిత 9",
    "author": "గురజాడ అప్పారావు",
    "style": "సామాజిక కవిత్వం",
    "era": "20వ శతాబ్దం",
    "language": "telugu"
  },
  {
    "text": "అభ్యుదయ కవులలో అగ్రగణ్యుడు\nఆధునిక తెలుగు కవిత్వంలో\nశ్రీశ్రీ మహాకవి\nశ్రమజీవుల నేస్తం",
    "title": "శ్రీశ్రీ కవిత 10",
    "author": "శ్రీశ్రీ",
    "style": "అభ్యుదయ కవిత్వం",
    "era": "20వ శతాబ్దం",
    "language": "telugu"
  },
  {
    "text": "స్నేహం గొప్పది\nమిత్రత్వం మంచిది\nకలిసి ఉంటే సుఖం\nప్రేమలో ఆనందం",
    "title": "కృష్ణశాస్త్రి కవిత 9",
    "author": "దేవులపల్లి కృష్ణశాస్త్రి",
    "style": "భావ కవిత్వం",
    "era": "20వ శతాబ్దం",
    "language": "telugu"
  },
  {
    "text": "ఇమ్ముగ చదువని నోరు\nకమ్ముకొను వైద్యమెఱుగని కయ్య\nఎమ్మెలు జూడని కన్ను\nలెట్టివి యున్నను గొట్టు చేతులు సుమతీ",
    "title": "సుమతీ శతకం 3",
    "author": "బద్దెన",
    "style": "కందం",
    "era": "14వ శతాబ్దం",
    "language": "telugu"
  },
  {
    "text": "మనసు నిర్మలంగా ఉంచుకో\nమాట మధురంగా మాట్లాడు\nచేతలు మెచ్చుకోదగినవిగా చేయి\nత్రికరణశుద్ధి ముఖ్యం",
    "title": "భర్తృహరి సుభాషితం 21",
    "author": "భర్తృహరి",
    "style": "సుభాషిత శతకం",
    "era": "ప్రాచీన",
    "language": "telugu"
  },
  {
    "text": "చెట్టు ఫలాలతో వంగుతుంది\nమేఘం నీటి బరువుతో కింద వస్తుంది\nసజ్జనులు సంపదతో వినయంగా ఉంటారు\nఇది ఉత్తముల లక్షణం",
    "title": "భర్తృహరి సుభాషితం 7",
    "author": "భర్తృహరి",
    "style": "సుభాషిత శతకం",
    "era": "ప్రాచీన",
    "language": "telugu"
  },
  {
    "text": "నన్నయ భారతంలో\nనవ రసాలు వెలిసెను\nవీర రసంతో పాటు\nకరుణ శృంగార రసాలు",
    "title": "నన్నయ పద్యం 13",
    "author": "నన్నయ",
    "style": "మహాభారతం",
    "era": "11వ శతాబ్దం",
    "language": "telugu"
  },
  {
    "text": "కవితా ప్రవాహమందు కవిసార్వభౌముడు\nపద్య రచనలో పండితుడు\nసాహిత్య సేవలో సార్వభౌమ బిరుదం\nశ్రీనాథుని కీర్తి శాశ్వతం",
    "title": "శ్రీనాథ పద్యం 16",
    "author": "శ్రీనాథుడు",
    "style": "ప్రబంధం",
    "era": "15వ శతాబ్దం",
    "language": "telugu"
  },
  {
    "text": "అసాధ్యమైనది సాధించాలంటే\nప్రయత్నం చేయాలి\nప్రయత్నం లేకుండా ఫలితం రాదు\nసాధన చేయాలి సదా",
    "title": "భర్తృహరి సుభాషితం 9",
    "author": "భర్తృహరి",
    "style": "సుభాషిత శతకం",
    "era": "ప్రాచీన",
    "language": "telugu"
  },
  {
    "text": "మహాకవి బిరుదం పొంది\nమహోన్నత స్థానంలో నిలిచాడు\nతెలుగు కవిత్వంలో\nతేజోమూర్తిగా వెలిగాడు",
    "title": "శ్రీశ్రీ కవిత 23",
    "author": "శ్రీశ్రీ",
    "style": "అభ్యుదయ కవిత్వం",
    "era": "20వ శతాబ్దం",
    "language": "telugu"
  },
  {
    "text": "నాదోపాసన నారాయణ సేవ\nసంగీతమందు సర్వమూ ఉన్నది\nత్యాగరాజు నాద బ్రహ్మను\nరాముని పాదాలకు సమర్పించెను",
    "title": "త్యాగరాజ కీర్తన 19",
    "author": "త్యాగరాజు",
    "style": "కర్ణాటక సంగీతం",
    "era": "18వ శతాబ్దం",
    "language": "telugu"
  },
  {
    "text": "సినిమా పాటలలో సామాజిక స్పృహ\nసాహిత్యంలో సమాజ చిత్రణ\nశ్రీశ్రీ బహుముఖ ప్రతిభ\nశతాబ్దాలకు వెలుగు",
    "title": "శ్రీశ్రీ కవిత 21",
    "author": "శ్రీశ్రీ",
    "style": "అభ్యుదయ కవిత్వం",
    "era": "20వ శతాబ్దం",
    "language": "telugu"
  },
  {
    "text": "బోనాల పండుగ బొమ్మల సంబరం\nమహిషాసుర మర్దిని మాయమ్మ రూపం\nతల్లి దేవత పూజ తరతరాల సంప్రదాయం",
    "title": "జానపద గేయం 19",
    "author": "జానపద",
    "style": "గేయం",
    "era": "సంప్రదాయ",
    "language": "telugu"
  },
  {
    "text": "చేను చెడ్డ సేద్యగాడు చెడ్డను చెప్పు\nఇల్లు చెడ్డ ఇల్లాలు చెడ్డనును\nతనకు చెడ్డ తానే తీరు చెప్పు\nవిశ్వదాభిరామ వినురవేమ",
    "title": "వేమన పద్యం 20",
    "author": "వేమన",
    "style": "ఆట వెలది",
    "era": "18వ శతాబ్దం",
    "language": "telugu"
  },
  {
    "text": "దానం చేయడం ధర్మం\nపుచ్చుకోవడం పాపం కాదు\nఇవ్వడంలో ఆనందం ఇరువురికీ",
    "title": "నీతి పద్యం 14",
    "author": "సంప్రదాయ",
    "style": "నీతి శతకం",
    "era": "సంప్రదాయ",
    "language": "telugu"
  },
  {
    "text": "కుమ్మరి కుండలు కుమ్మరి మట్టి\nకళాకారుని చేతిలో కళాఖండం\nమట్టి బొమ్మలు మనసు దోచే",
    "title": "జానపద గేయం 24",
    "author": "జానపద",
    "style": "గేయం",
    "era": "సంప్రదాయ",
    "language": "telugu"
  },
  {
    "text": "ఉదయం సూర్యుడు\nసాయంత్రం చందమామ\nప్రకృతి లయ అందం\nజీవిత గమనం",
    "title": "కృష్ణశాస్త్రి కవిత 5",
    "author": "దేవులపల్లి కృష్ణశాస్త్రి",
    "style": "భావ కవిత్వం",
    "era": "20వ శతాబ్దం",
    "language": "telugu"
  },
  {
    "text": "గయోపాఖ్యానం\nపురాణ కథ\nభక్తి మార్గం\nమోక్ష సాధనం",
    "title": "చిలకమర్తి రచన 1",
    "author": "చిలకమర్తి",
    "style": "హాస్య కవిత్వం",
    "era": "20వ శతాబ్దం",
    "language": "telugu"
  },
  {
    "text": "జ్ఞానం సంపాదించు జీవితం మెరుగుపడు\nమూర్ఖంగా ఉండకు ముందుకు నడు",
    "title": "నీతి పద్యం 28",
    "author": "సంప్రదాయ",
    "style": "నీతి శతకం",
    "era": "సంప్రదాయ",
    "language": "telugu"
  },
  {
    "text": "తెలుగు భాష సౌందర్యం\nతేజోవంతంగా చూపెను\nపద్య రచనలో పటుత్వం\nప్రదర్శించిన మహాకవి",
    "title": "నన్నయ పద్యం 14",
    "author": "నన్నయ",
    "style": "మహాభారతం",
    "era": "11వ శతాబ్దం",
    "language": "telugu"
  },
  {
    "text": "విప్లవ కవిత్వానికి వీరుడు\nప్రజా కవిత్వానికి ప్రతీక\nశ్రీశ్రీ మహాకవి\nశాశ్వత కీర్తి గడించాడు",
    "title": "శ్రీశ్రీ కవిత 19",
    "author": "శ్రీశ్రీ",
    "style": "అభ్యుదయ కవిత్వం",
    "era": "20వ శతాబ్దం",
    "language": "telugu"
  },
  {
    "text": "ప్రవాస కాలంలో ప్రకృతి వర్ణన\nస్వదేశంపై ప్రేమ\nకృష్ణశాస్త్రి కవిత్వంలో\nకనబడే భావాలు",
    "title": "కృష్ణశాస్త్రి కవిత 15",
    "author": "దేవులపల్లి కృష్ణశాస్త్రి",
    "style": "భావ కవిత్వం",
    "era": "20వ శతాబ్దం",
    "language": "telugu"
  },
  {
    "text": "కవి సార్వభౌమా\nశ్రీనాథుని బిరుదం\nకవిత్వ శిఖరం\nసాహిత్య రత్నం",
    "title": "శ్రీనాథ పద్యం 4",
    "author": "శ్రీనాథుడు",
    "style": "ప్రబంధం",
    "era": "15వ శతాబ్దం",
    "language": "telugu"
  },
  {
    "text": "పంచభూతాలు పంచప్రాణాలు\nప్రకృతి సృష్టి అద్భుతం\nమానవ జన్మ మహత్తరం\nసద్వినియోగం చేసుకో",
    "title": "భర్తృహరి సుభాషితం 28",
    "author": "భర్తృహరి",
    "style": "సుభాషిత శతకం",
    "era": "ప్రాచీన",
    "language": "telugu"
  },
  {
    "text": "సూర్యుడు లేని పగలు లేదు\nచంద్రుడు లేని రాత్రి లేదు\nవిద్య లేని మానవుడు\nపశువుతో సమానం",
    "title": "భర్తృహరి సుభాషితం 19",
    "author": "భర్తృహరి",
    "style": "సుభాషిత శతకం",
    "era": "ప్రాచీన",
    "language": "telugu"
  },
  {
    "text": "కాలుజారినంత కష్టము రాదయా\nమాటజారినంత మానము పోవు\nచేతిలో తప్పు చేయకుండవలయు\nవిశ్వదాభిరామ వినురవేమ",
    "title": "వేమన పద్యం 28",
    "author": "వేమన",
    "style": "ఆట వెలది",
    "era": "18వ శతాబ్దం",
    "language": "telugu"
  },
  {
    "text": "బ్రహ్మోత్సవములందు బంగారు రథమెక్కి\nస్వామి వీధులందు విహరించేను\nభక్తులకు దర్శనమిచ్చి భాగ్యమిచ్చేను",
    "title": "అన్నమయ్య కీర్తన 17",
    "author": "అన్నమయ్య",
    "style": "సంకీర్తన",
    "era": "15వ శతాబ్దం",
    "language": "telugu"
  },
  {
    "text": "కష్టపడి సంపాదించు కలిమి కలుగు\nఇతరుల సొమ్ము ఇష్టపడకు",
    "title": "నీతి పద్యం 25",
    "author": "సంప్రదాయ",
    "style": "నీతి శతకం",
    "era": "సంప్రదాయ",
    "language": "telugu"
  },
  {
    "text": "కోడి కూసింది కోకిల పాడింది\nకాకి అరిచింది కంఠమెత్తి\nపిట్ట చిట్టని పిల్ల పాడింది\nగొంతు విప్పి గోల చేసింది",
    "title": "జానపద గేయం 9",
    "author": "జానపద",
    "style": "గేయం",
    "era": "సంప్రదాయ",
    "language": "telugu"
  },
  {
    "text": "తెలుగు సాహిత్యంలో తేజోమూర్తి\nకవిత్వ ప్రపంచంలో కమనీయ రూపం\nపద్య సౌందర్యంలో పరిపూర్ణత\nశ్రీనాథుడు సాహిత్య సార్వభౌముడు",
    "title": "శ్రీనాథ పద్యం 30",
    "author": "శ్రీనాథుడు",
    "style": "ప్రబంధం",
    "era": "15వ శతాబ్దం",
    "language": "telugu"
  },
  {
    "text": "నీతి లేని వాడు నిర్గతి యగు\nజాతి లేని వాడు జారిపోవు\nమతము లేని వాడు మరణించినంతే\nవిశ్వదాభిరామ వినురవేమ",
    "title": "వేమన పద్యం 26",
    "author": "వేమన",
    "style": "ఆట వెలది",
    "era": "18వ శతాబ్దం",
    "language": "telugu"
  },
  {
    "text": "ముత్యాల సరాలు కావ్యంలో\nమధుర గేయాలు రచించెను\nతెలుగు భాష అందాలు\nతేనెలా తీపిగా చూపెను",
    "title": "గురజాడ కవిత 17",
    "author": "గురజాడ అప్పారావు",
    "style": "సామాజిక కవిత్వం",
    "era": "20వ శతాబ్దం",
    "language": "telugu"
  },
  {
    "text": "గ్రామీణ జీవితం\nసరళంగా ఉంటుంది\nప్రకృతి సాన్నిహిత్యం\nఆరోగ్యకరం",
    "title": "ఆధునిక కవిత 23",
    "author": "ఆధునిక కవి",
    "style": "వచన కవిత",
    "era": "21వ శతాబ్దం",
    "language": "telugu"
  },
  {
    "text": "కవిత్రయంలో మొదటివాడు\nకావ్య సృష్టికి ఆద్యుడు\nతెలుగు సాహిత్య పితామహుడు\nనన్నయ భట్టు వందనం",
    "title": "నన్నయ పద్యం 2",
    "author": "నన్నయ",
    "style": "మహాభారతం",
    "era": "11వ శతాబ్దం",
    "language": "telugu"
  },
  {
    "text": "మహాప్రస్థానం నా కవిత్వం\nమార్పు కోసం పిలుపు\nప్రజల కోసం పాట\nశ్రీశ్రీ కవిత్వం",
    "title": "శ్రీశ్రీ కవిత 1",
    "author": "శ్రీశ్రీ",
    "style": "అభ్యుదయ కవిత్వం",
    "era": "20వ శతాబ్దం",
    "language": "telugu"
  },
  {
    "text": "ఆధునిక తెలుగు వచన సాహిత్యంలో\nఆద్యులలో ఒకరు చిలకమర్తి\nనవల నాటక కథా రంగాలలో\nనవ్య ప్రయోగాలు చేసెను",
    "title": "చిలకమర్తి రచన 21",
    "author": "చిలకమర్తి",
    "style": "హాస్య కవిత్వం",
    "era": "20వ శతాబ్దం",
    "language": "telugu"
  },
  {
    "text": "మౌనం సర్వార్థ సాధకం\nమాట్లాడకుండా ఉంటే తప్పులు రావు\nమౌనంగా ఉన్నవాడు మహాత్ముడు\nభర్తృహరి నీతి వాక్యం",
    "title": "భర్తృహరి సుభాషితం 2",
    "author": "భర్తృహరి",
    "style": "సుభాషిత శతకం",
    "era": "ప్రాచీన",
    "language": "telugu"
  },
  {
    "text": "ఈతచెట్టు కింద ఈ పిల్ల\nతాళిచెట్టు కింద తల్లి\nమామిడిచెట్టు కింద మామ\nచింతచెట్టు కింద చిన్నారి",
    "title": "జానపద గేయం 11",
    "author": "జానపద",
    "style": "గేయం",
    "era": "సంప్రదాయ",
    "language": "telugu"
  },
  {
    "text": "ఘన రాగాలలో గాన మాధుర్యం\nరామ నామంలో రసానుభవం\nత్యాగయ్య కీర్తనలలో\nతేలిపోయే ఆనందం",
    "title": "త్యాగరాజ కీర్తన 22",
    "author": "త్యాగరాజు",
    "style": "కర్ణాటక సంగీతం",
    "era": "18వ శతాబ్దం",
    "language": "telugu"
  },
  {
    "text": "హరిదాసులందరికి హారతి పట్టేము\nసంకీర్తనలందు సంతోషమందు\nభజన చేసేము భక్తితో స్వామికి",
    "title": "అన్నమయ్య కీర్తన 21",
    "author": "అన్నమయ్య",
    "style": "సంకీర్తన",
    "era": "15వ శతాబ్దం",
    "language": "telugu"
  },
  {
    "text": "రాజరాజ నరేంద్రుని ఆస్థానంలో\nరాజమర్యాద పొందెను\nమహాభారతం రచించమని\nరాజు ఆదేశమిచ్చెను",
    "title": "నన్నయ పద్యం 4",
    "author": "నన్నయ",
    "style": "మహాభారతం",
    "era": "11వ శతాబ్దం",
    "language": "telugu"
  },
  {
    "text": "నగర జీవితం\nఒత్తిడి ఎక్కువ\nశాంతి కోసం\nమనసు ప్రశాంతత కావాలి",
    "title": "ఆధునిక కవిత 24",
    "author": "ఆధునిక కవి",
    "style": "వచన కవిత",
    "era": "21వ శతాబ్దం",
    "language": "telugu"
  },
  {
    "text": "భీమేశ్వర పురాణం\nవేదాల సారం\nశివుని మహిమ\nభక్తి మార్గం",
    "title": "శ్రీనాథ పద్యం 3",
    "author": "శ్రీనాథుడు",
    "style": "ప్రబంధం",
    "era": "15వ శతాబ్దం",
    "language": "telugu"
  },
  {
    "text": "గోదావరి తీరంలో\nభద్రాద్రి గుట్టపైన\nవెలసిన శ్రీరాముడు\nరామదాసు ఆరాధ్యుడు",
    "title": "రామదాసు కీర్తన 7",
    "author": "రామదాసు",
    "style": "భక్తి కీర్తన",
    "era": "17వ శతాబ్దం",
    "language": "telugu"
  },
  {
    "text": "తల్లి తండ్రి మాట తలగు దలగు వింటే\nబుద్ధి హీనులగుదురు పుత్రులు\nగురుదేవుల మాట గ్రహించకున్న\nమూర్ఖులౌదురయ్య సుమతీ",
    "title": "సుమతీ శతకం 9",
    "author": "బద్దెన",
    "style": "కందం",
    "era": "14వ శతాబ్దం",
    "language": "telugu"
  },
  {
    "text": "పల్లెటూరి పిల్లగాడా\nపాటలు పాడుమురా\nచల్ల చల్లని వెన్నెలలో\nచక్కగా ఆడుమురా",
    "title": "జానపద గేయం 10",
    "author": "జానపద",
    "style": "గేయం",
    "era": "సంప్రదాయ",
    "language": "telugu"
  },
  {
    "text": "అబద్ధం చెప్పకు అపఖ్యాతి వచ్చును\nసత్యమే చెప్పు సన్మానం పొందు",
    "title": "నీతి పద్యం 22",
    "author": "సంప్రదాయ",
    "style": "నీతి శతకం",
    "era": "సంప్రదాయ",
    "language": "telugu"
  },
  {
    "text": "స్వరరాగ సుధారసం\nసంగీత సారం\nరాముని కీర్తన రమణీయం\nత్యాగరాజు గానం",
    "title": "త్యాగరాజ కీర్తన 17",
    "author": "త్యాగరాజు",
    "style": "కర్ణాటక సంగీతం",
    "era": "18వ శతాబ్దం",
    "language": "telugu"
  },
  {
    "text": "అసూయ పడకు అందరినీ మెచ్చు\nఇతరుల విజయాలకు ఇష్టపడు",
    "title": "నీతి పద్యం 16",
    "author": "సంప్రదాయ",
    "style": "నీతి శతకం",
    "era": "సంప్రదాయ",
    "language": "telugu"
  },
  {
    "text": "పని చేయువాడే పట్టాభిషేకుడు\nసోమరి వాడు సొంతము కోల్పోవు\nకష్టపడెడివాడు కామధేనువు వంటివాడు\nశ్రమయే ధనము సుమతీ",
    "title": "సుమతీ శతకం 23",
    "author": "బద్దెన",
    "style": "కందం",
    "era": "14వ శతాబ్దం",
    "language": "telugu"
  },
  {
    "text": "వడ్రంగి చెక్కలో వస్తువులు చేసేరు\nమర వస్తువులు మన ఇంట్లో ఉన్నవి\nచేతి వృత్తులన్నీ చేవగల నేర్పు",
    "title": "జానపద గేయం 27",
    "author": "జానపద",
    "style": "గేయం",
    "era": "సంప్రదాయ",
    "language": "telugu"
  },
  {
    "text": "విద్య నేర్చుకో విజయం సాధించు\nమంచి చదువుకో మంచి బ్రతుకు\nశ్రమ పడితే సుఖం వచ్చును\nసత్యమే జయం సదా గెలుచు",
    "title": "ఆధునిక కవిత 3",
    "author": "ఆధునిక కవి",
    "style": "వచన కవిత",
    "era": "21వ శతాబ్దం",
    "language": "telugu"
  },
  {
    "text": "అమ్మ అనే మాట అమృతం వంటిది\nనాన్న అనే మాట నమ్మకం వంటిది\nకుటుంబమ్ అనే మాట కళ్ళ వెలుగు\nప్రేమ అనే మాట ప్రాణం వంటిది",
    "title": "ఆధునిక కవిత 2",
    "author": "ఆధునిక కవి",
    "style": "వచన కవిత",
    "era": "21వ శతాబ్దం",
    "language": "telugu"
  },
  {
    "text": "నైషధం కావ్యం\nనలదమయంతి కథ\nప్రేమ కథనం\nవిరహ వేదన",
    "title": "శ్రీనాథ పద్యం 11",
    "author": "శ్రీనాథుడు",
    "style": "ప్రబంధం",
    "era": "15వ శతాబ్దం",
    "language": "telugu"
  },
  {
    "text": "మంత్రం రహస్యంగా ఉంచితే ఫలిస్తుంది\nధనం రహస్యంగా ఉంచితే పెరుగుతుంది\nతప్పు రహస్యంగా ఉంచితే తగ్గుతుంది\nరహస్యం రక్షించాలి",
    "title": "భర్తృహరి సుభాషితం 16",
    "author": "భర్తృహరి",
    "style": "సుభాషిత శతకం",
    "era": "ప్రాచీన",
    "language": "telugu"
  },
  {
    "text": "ఊర్వశి నాటకం ఉత్తమ రచన\nకృష్ణశాస్త్రి నాటక కళ\nతెలుగు రంగస్థలంపై\nతేజస్సుగా నిలిచెను",
    "title": "కృష్ణశాస్త్రి కవిత 14",
    "author": "దేవులపల్లి కృష్ణశాస్త్రి",
    "style": "భావ కవిత్వం",
    "era": "20వ శతాబ్దం",
    "language": "telugu"
  },
  {
    "text": "కవిత్రయ యుగంలో\nకమనీయ ప్రారంభం\nనన్నయ కవిత్వం\nనూతన మార్గ దర్శనం",
    "title": "నన్నయ పద్యం 23",
    "author": "నన్నయ",
    "style": "మహాభారతం",
    "era": "11వ శతాబ్దం",
    "language": "telugu"
  },
  {
    "text": "ధర్మ రక్షణ కోసం\nపాండవులు పోరాడిరి\nకురుక్షేత్ర యుద్ధంలో\nధర్మం గెలిచింది",
    "title": "తిక్కన పద్యం 2",
    "author": "తిక్కన",
    "style": "మహాభారతం",
    "era": "13వ శతాబ్దం",
    "language": "telugu"
  },
  {
    "text": "అక్షరాలు నేర్చుకొని అన్నీ తెలుసుకో\nచదువు నేర్చుకొని చక్కగా బ్రతుకు\nవిద్యావంతులై విజయం సాధించు",
    "title": "జానపద గేయం 30",
    "author": "జానపద",
    "style": "గేయం",
    "era": "సంప్రదాయ",
    "language": "telugu"
  },
  {
    "text": "పర్యావరణం కాపాడండి\nచెట్లు నాటండి\nప్రకృతి రక్షణ\nభవిష్యత్తు కోసం",
    "title": "ఆధునిక కవిత 27",
    "author": "ఆధునిక కవి",
    "style": "వచన కవిత",
    "era": "21వ శతాబ్దం",
    "language": "telugu"
  },
  {
    "text": "ఆకాశంలో నక్షత్రాలు\nమెరుస్తున్నాయి\nచంద్రుడు లేని రాత్రిలో\nతారలే వెలుగు",
    "title": "కృష్ణశాస్త్రి కవిత 2",
    "author": "దేవులపల్లి కృష్ణశాస్త్రి",
    "style": "భావ కవిత్వం",
    "era": "20వ శతాబ్దం",
    "language": "telugu"
  },
  {
    "text": "దేశమును ప్రేమించు దేశ భక్తుడవుండు\nదేశ హితము కోరు దీప్తిగ బ్రతుకు\nదేశ సేవలో దివ్యమైన ఆనందము\nదేశ ప్రేమే ధర్మము సుమతీ",
    "title": "సుమతీ శతకం 21",
    "author": "బద్దెన",
    "style": "కందం",
    "era": "14వ శతాబ్దం",
    "language": "telugu"
  },
  {
    "text": "పోతన భాగవతము పూజనీయమైనది\nతెలుగులో వ్రాసిన తేజో మయము\nభక్తి రసములో భగవంతుని చూపు\nసహజ కవిత్వము సాహిత్య రత్నము",
    "title": "భాగవత పద్యం 7",
    "author": "పోతన",
    "style": "ఉత్పలమాల",
    "era": "15వ శతాబ్దం",
    "language": "telugu"
  },
  {
    "text": "రామ కథా సుధ రసము\nపానం చేసేవారికి\nమోక్ష మార్గం తెలిసేను\nరామ భక్తి ఫలమిదే",
    "title": "త్యాగరాజ కీర్తన 3",
    "author": "త్యాగరాజు",
    "style": "కర్ణాటక సంగీతం",
    "era": "18వ శతాబ్దం",
    "language": "telugu"
  },
  {
    "text": "కర్ణాటక సంగీత కర్ణధారుడు\nరామ భక్తి రాగాల నిధి\nశతాబ్దాలకు సంగీత వెలుగు\nత్యాగరాజు సంగీత ప్రభువు",
    "title": "త్యాగరాజ కీర్తన 25",
    "author": "త్యాగరాజు",
    "style": "కర్ణాటక సంగీతం",
    "era": "18వ శతాబ్దం",
    "language": "telugu"
  },
  {
    "text": "మరుత్తరాట్చరిత్రము\nమహాకావ్య రచన\nరాజుల చరిత్ర\nధీర కథనం",
    "title": "శ్రీనాథ పద్యం 6",
    "author": "శ్రీనాథుడు",
    "style": "ప్రబంధం",
    "era": "15వ శతాబ్దం",
    "language": "telugu"
  },
  {
    "text": "అనఘమైన చెట్టు అడవిలో నుండును\nకాగితంబు లేక కర్ణుడుండు\nచిన్నవాని యొద్ద చీటి లేకుండును\nవిశ్వదాభిరామ వినురవేమ",
    "title": "వేమన పద్యం 9",
    "author": "వేమన",
    "style": "ఆట వెలది",
    "era": "18వ శతాబ్దం",
    "language": "telugu"
  },
  {
    "text": "పువ్వు పూసింది\nతుమ్మెద వచ్చింది\nప్రకృతి సయ్యాట\nసృష్టి అందం",
    "title": "కృష్ణశాస్త్రి కవిత 6",
    "author": "దేవులపల్లి కృష్ణశాస్త్రి",
    "style": "భావ కవిత్వం",
    "era": "20వ శతాబ్దం",
    "language": "telugu"
  },
  {
    "text": "కోతి చేతి కొబ్బరికాయ చందమాయె\nవీటి వీటి చూపు వెర్రి గాను\nతన దోషమెరుగక తలదాచుకొను నట్లు\nవిశ్వదాభిరామ వినురవేమ",
    "title": "వేమన పద్యం 18",
    "author": "వేమన",
    "style": "ఆట వెలది",
    "era": "18వ శతాబ్దం",
    "language": "telugu"
  },
  {
    "text": "బంటురీతి కొలువు చేసే\nభక్తుడు నేను రామచంద్రా\nనీ దాసుడను నన్ను గావు\nకరుణా సాగరా రామా",
    "title": "త్యాగరాజ కీర్తన 7",
    "author": "త్యాగరాజు",
    "style": "కర్ణాటక సంగీతం",
    "era": "18వ శతాబ్దం",
    "language": "telugu"
  },
  {
    "text": "అంత్యప్రాస అభ్యుదయం\nఆధునిక కవిత్వ శైలి\nశ్రీశ్రీ ప్రవేశపెట్టిన\nకొత్త దారులు",
    "title": "శ్రీశ్రీ కవిత 7",
    "author": "శ్రీశ్రీ",
    "style": "అభ్యుదయ కవిత్వం",
    "era": "20వ శతాబ్దం",
    "language": "telugu"
  },
  {
    "text": "ప్రకృతిని ప్రేమించిన కవి\nపల్లెలను ప్రశంసించిన కవి\nకృష్ణశాస్త్రి కవిత్వం\nకాలాతీతంగా నిలిచెను",
    "title": "కృష్ణశాస్త్రి కవిత 22",
    "author": "దేవులపల్లి కృష్ణశాస్త్రి",
    "style": "భావ కవిత్వం",
    "era": "20వ శతాబ్దం",
    "language": "telugu"
  },
  {
    "text": "తెలుగు వచన సాహిత్యంలో\nతేజోమూర్తిగా నిలిచెను\nహాస్య రసప్రదాతగా హర్షం కలిగించెను\nచిలకమర్తి కీర్తి కాలాతీతం",
    "title": "చిలకమర్తి రచన 18",
    "author": "చిలకమర్తి",
    "style": "హాస్య కవిత్వం",
    "era": "20వ శతాబ్దం",
    "language": "telugu"
  },
  {
    "text": "మేకతోలు క్రప్పి మింగెడు తోడేలు\nతోలు తీయగానే తోచు తప్పు\nమంచివాని వేషము మనిషికి తెలియదు\nవిశ్వదాభిరామ వినురవేమ",
    "title": "వేమన పద్యం 19",
    "author": "వేమన",
    "style": "ఆట వెలది",
    "era": "18వ శతాబ్దం",
    "language": "telugu"
  },
  {
    "text": "వేద పాండిత్యంతో వెలిగెను\nశాస్త్ర పాండిత్యంతో శోభిల్లెను\nకావ్య పాండిత్యంతో కాంతులీనెను\nనన్నయ త్రిపాండిత్యుడు",
    "title": "నన్నయ పద్యం 16",
    "author": "నన్నయ",
    "style": "మహాభారతం",
    "era": "11వ శతాబ్దం",
    "language": "telugu"
  },
  {
    "text": "సముద్రం ఎంత లోతో తెలియదు\nమహాత్ముని మనసు ఎంత లోతో తెలియదు\nచిన్న చెరువు లోతు త్వరగా తెలుస్తుంది\nమూర్ఖుడి మనసు ఇట్టే కనబడుతుంది",
    "title": "భర్తృహరి సుభాషితం 22",
    "author": "భర్తృహరి",
    "style": "సుభాషిత శతకం",
    "era": "ప్రాచీన",
    "language": "telugu"
  },
  {
    "text": "ఓ రంగశాయి నన్ను గావు\nశ్రీరంగనాథా వందనం\nరంగని సేవించేవారికి\nమోక్షము కరతలామలకం",
    "title": "త్యాగరాజ కీర్తన 9",
    "author": "త్యాగరాజు",
    "style": "కర్ణాటక సంగీతం",
    "era": "18వ శతాబ్దం",
    "language": "telugu"
  },
  {
    "text": "కవిబ్రహ్మ అని కొనియాడబడెను\nకావ్య రచనలో కమనీయత చూపెను\nపద్య శైలిలో పండిత మన్ననలు\nతిక్కన మహాకవి తరతరాల కీర్తి",
    "title": "తిక్కన పద్యం 16",
    "author": "తిక్కన",
    "style": "మహాభారతం",
    "era": "13వ శతాబ్దం",
    "language": "telugu"
  },
  {
    "text": "కంసవధ కృష్ణుని కర్తవ్యము\nమామను మర్దించి మధురను ఏలెను\nయదువంశమందు యశస్సు పెంచెను\nధర్మస్థాపన ధర్మ రక్షణ",
    "title": "భాగవత పద్యం 17",
    "author": "పోతన",
    "style": "ఉత్పలమాల",
    "era": "15వ శతాబ్దం",
    "language": "telugu"
  },
  {
    "text": "మంచి స్నేహితుడు మాణిక్యం వంటివాడు\nచెడ్డ స్నేహితుడు చెడుగు చేస్తాడు\nస్నేహం ఎంచుకునేటప్పుడు\nజాగ్రత్తగా ఉండాలి",
    "title": "భర్తృహరి సుభాషితం 13",
    "author": "భర్తృహరి",
    "style": "సుభాషిత శతకం",
    "era": "ప్రాచీన",
    "language": "telugu"
  },
  {
    "text": "హాస్య చతురత\nవ్యంగ్య రచన\nసమాజ దోషాలు\nహాస్యంలో మందలింపు",
    "title": "చిలకమర్తి రచన 10",
    "author": "చిలకమర్తి",
    "style": "హాస్య కవిత్వం",
    "era": "20వ శతాబ్దం",
    "language": "telugu"
  },
  {
    "text": "సంగీతం ఆత్మకు ఆహారం\nకళలు జీవితానికి వెలుగు\nసృజనాత్మకత పెంచండి\nకళల్ని ఆస్వాదించండి",
    "title": "ఆధునిక కవిత 29",
    "author": "ఆధునిక కవి",
    "style": "వచన కవిత",
    "era": "21వ శతాబ్దం",
    "language": "telugu"
  },
  {
    "text": "తిక్కన సోమయాజి తెలుగు సాహిత్య భూషణం\nకవిత్రయంలో కమనీయ స్థానం\nభారత కావ్యంలో భాసుర కీర్తి\nతిక్కన మహాకవి తరతరాల వెలుగు",
    "title": "తిక్కన పద్యం 25",
    "author": "తిక్కన",
    "style": "మహాభారతం",
    "era": "13వ శతాబ్దం",
    "language": "telugu"
  },
  {
    "text": "దసరా పండగలో దుర్గమ్మ పూజలు\nతొమ్మిది రోజులు తల్లికి నోములు\nవిజయదశమిలో విజయాలు వచ్చేను",
    "title": "జానపద గేయం 21",
    "author": "జానపద",
    "style": "గేయం",
    "era": "సంప్రదాయ",
    "language": "telugu"
  },
  {
    "text": "కృష్ణ పక్షంలో\nకృష్ణ పక్షమ్ము కమ్మెను\nచంద్రుడు తగ్గి పోయెను\nతారలు వెలిగెను",
    "title": "కృష్ణశాస్త్రి కవిత 1",
    "author": "దేవులపల్లి కృష్ణశాస్త్రి",
    "style": "భావ కవిత్వం",
    "era": "20వ శతాబ్దం",
    "language": "telugu"
  },
  {
    "text": "నమ్మినవానిని నమ్మకద్రోహము చేయకు\nద్రోహి చేసిన ద్రోహమొచ్చును\nnчестము విశ్వాసము నిలుపుకొనవలయు\nనమ్మకమే నిజము సుమతీ",
    "title": "సుమతీ శతకం 22",
    "author": "బద్దెన",
    "style": "కందం",
    "era": "14వ శతాబ్దం",
    "language": "telugu"
  },
  {
    "text": "రాజసభలో రాజమర్యాద పొందెను\nకవిత్వమందు కీర్తి గడించెను\nపండితులు మెచ్చిన పద్యాలు చెప్పెను\nశ్రీనాథుని ప్రతిభ శ్రేష్ఠమైనది",
    "title": "శ్రీనాథ పద్యం 17",
    "author": "శ్రీనాథుడు",
    "style": "ప్రబంధం",
    "era": "15వ శతాబ్దం",
    "language": "telugu"
  },
  {
    "text": "క్రీడాభిరామం నాటకం\nశృంగార హాస్యం\nరాజసభా వర్ణన\nకవితా చాతుర్యం",
    "title": "శ్రీనాథ పద్యం 10",
    "author": "శ్రీనాథుడు",
    "style": "ప్రబంధం",
    "era": "15వ శతాబ్దం",
    "language": "telugu"
  },
  {
    "text": "విద్యావంతులందరూ\nవినయంతో గుర్తుంచుకోవాలి\nగురజాడ సందేశాలు\nగొప్పవని తెలుసుకోవాలి",
    "title": "గురజాడ కవిత 22",
    "author": "గురజాడ అప్పారావు",
    "style": "సామాజిక కవిత్వం",
    "era": "20వ శతాబ్దం",
    "language": "telugu"
  },
  {
    "text": "శ్రీరామ నవమి పండుగ\nభద్రాచలంలో బాగుంటుంది\nరామదాసు స్థాపించిన\nరామ కల్యాణం జరుగుతుంది",
    "title": "రామదాసు కీర్తన 14",
    "author": "రామదాసు",
    "style": "భక్తి కీర్తన",
    "era": "17వ శతాబ్దం",
    "language": "telugu"
  },
  {
    "text": "తెలంగాణ నేల మా తల్లి నేల\nఆంధ్ర నేల మా ఆత్మ నేల\nతెలుగు భాష మా ప్రాణ భాష\nతెలుగు జాతి మా గర్వ జాతి",
    "title": "ఆధునిక కవిత 15",
    "author": "ఆధునిక కవి",
    "style": "వచన కవిత",
    "era": "21వ శతాబ్దం",
    "language": "telugu"
  },
  {
    "text": "రావే రావే మా అమ్మా\nరమ్ము రమ్ము రా అమ్మా\nపాలు పోయవమ్మా\nపాప నవ్వేనమ్మా",
    "title": "జానపద గేయం 8",
    "author": "జానపద",
    "style": "గేయం",
    "era": "సంప్రదాయ",
    "language": "telugu"
  },
  {
    "text": "సామాజిక న్యాయం కోసం\nసాహిత్యంలో పోరాడాడు\nపేదల పక్షం వహించి\nప్రజా కవిగా నిలిచాడు",
    "title": "శ్రీశ్రీ కవిత 17",
    "author": "శ్రీశ్రీ",
    "style": "అభ్యుదయ కవిత్వం",
    "era": "20వ శతాబ్దం",
    "language": "telugu"
  },
  {
    "text": "భద్రాచల రామా\nభక్త వత్సలా రామా\nరామదాసుని కాపాడు\nకరుణా సాగరా రామా",
    "title": "రామదాసు కీర్తన 4",
    "author": "రామదాసు",
    "style": "భక్తి కీర్తన",
    "era": "17వ శతాబ్దం",
    "language": "telugu"
  },
  {
    "text": "పల్లెటూరి పిల్లగాడా\nపల్లెటూరి అందాలు\nప్రకృతి ఒడిలో ఆనందం\nపంట చేల సౌందర్యం",
    "title": "కృష్ణశాస్త్రి కవిత 3",
    "author": "దేవులపల్లి కృష్ణశాస్త్రి",
    "style": "భావ కవిత్వం",
    "era": "20వ శతాబ్దం",
    "language": "telugu"
  },
  {
    "text": "పాపనాశము తీర్థము పావనమయ్యను\nస్వామి పుష్కరిణిలో స్నానమాడితి\nపుణ్యతీర్థమందు పునీతుడైతి",
    "title": "అన్నమయ్య కీర్తన 15",
    "author": "అన్నమయ్య",
    "style": "సంకీర్తన",
    "era": "15వ శతాబ్దం",
    "language": "telugu"
  },
  {
    "text": "పద్య కవిత్వంలో పరమోన్నతం\nప్రబంధ రచనలో ప్రథమ స్థానం\nకావ్య కళలో కళాన్విత రూపం\nశ్రీనాథుడు సాహిత్య సామ్రాట్టు",
    "title": "శ్రీనాథ పద్యం 29",
    "author": "శ్రీనాథుడు",
    "style": "ప్రబంధం",
    "era": "15వ శతాబ్దం",
    "language": "telugu"
  },
  {
    "text": "యుక్తి లేని పని యోగ్యము కాదు\nశక్తి లేని పని సాధ్యము కాదు\nబుద్ధి లేని తలపు బూటకమవును\nయుక్తి శక్తి బుద్ధి సుమతీ",
    "title": "సుమతీ శతకం 26",
    "author": "బద్దెన",
    "style": "కందం",
    "era": "14వ శతాబ్దం",
    "language": "telugu"
  },
  {
    "text": "మంచి మాట చెప్పు మధురంగా బ్రతుకు\nచెడ్డ మాట చెప్పు చెడిపోవును\nమాట మీద నడక మంచితనము\nమాట తీరు ముఖ్యము సుమతీ",
    "title": "సుమతీ శతకం 25",
    "author": "బద్దెన",
    "style": "కందం",
    "era": "14వ శతాబ్దం",
    "language": "telugu"
  },
  {
    "text": "కన్యాశుల్కం నాటకంలో\nమధురవాణి పాత్ర గొప్ప\nసామాజిక దురాచారాలు\nమార్పు రావాలని పిలుపు",
    "title": "గురజాడ కవిత 3",
    "author": "గురజాడ అప్పారావు",
    "style": "సామాజిక కవిత్వం",
    "era": "20వ శతాబ్దం",
    "language": "telugu"
  },
  {
    "text": "మంచి మాట మందు వంటిది\nచెడ్డమాట విషం వంటిది\nమాటల్లో మర్యాద ఉండాలి\nభర్తృహరి బోధన",
    "title": "భర్తృహరి సుభాషితం 8",
    "author": "భర్తృహరి",
    "style": "సుభాషిత శతకం",
    "era": "ప్రాచీన",
    "language": "telugu"
  },
  {
    "text": "నన్ను బ్రోవని నీకేమయ్య\nరామ చంద్రా నన్ను గావు\nనీవే తల్లి తండ్రివని\nనమ్మి నిన్ను వేడికొనుచు",
    "title": "త్యాగరాజ కీర్తన 4",
    "author": "త్యాగరాజు",
    "style": "కర్ణాటక సంగీతం",
    "era": "18వ శతాబ్దం",
    "language": "telugu"
  },
  {
    "text": "ఉడుకుచుందురు తల్లిదండ్రులు లేనివాడు\nఉపకారము చేయువారు లేనివాడు\nకడు పేదరికమునందు కలిమి లేనివాడు\nమడమలు త్రొక్కు నేస్తము లేనివాడు సుమతీ",
    "title": "సుమతీ శతకం 4",
    "author": "బద్దెన",
    "style": "కందం",
    "era": "14వ శతాబ్దం",
    "language": "telugu"
  },
  {
    "text": "సజ్జనులు సంపదలో వినయంగా ఉంటారు\nదుర్జనులు కొంచెంలో గర్వపడతారు\nసముద్రపు లోతు తెలియకున్నా\nచిన్న చెరువులు పొంగిపోతాయి",
    "title": "భర్తృహరి సుభాషితం 3",
    "author": "భర్తృహరి",
    "style": "సుభాషిత శతకం",
    "era": "ప్రాచీన",
    "language": "telugu"
  },
  {
    "text": "కుర్చీ బళ్ళెంకత్తే కొత్త బట్టలేసుకో\nపల్లకీలో ఊరేగు పంతులమ్మ వచ్చింది\nపిల్లల్ని బడికి పంపించు",
    "title": "జానపద గేయం 29",
    "author": "జానపద",
    "style": "గేయం",
    "era": "సంప్రదాయ",
    "language": "telugu"
  },
  {
    "text": "కలిమి ఉన్న వాడు కనికరము చూపు\nలేమి ఉన్న వాడు లీనమవును\nధనము లేకపోయె ధైర్యము ఉండవలె\nవిశ్వదాభిరామ వినురవేమ",
    "title": "వేమన పద్యం 30",
    "author": "వేమన",
    "style": "ఆట వెలది",
    "era": "18వ శతాబ్దం",
    "language": "telugu"
  },
  {
    "text": "చేపలు పట్టేరు చేతిలో వలతో\nనదిలో సముద్రంలో నిత్య జీవితం\nచేపల వేట చేతి తెలివి",
    "title": "జానపద గేయం 28",
    "author": "జానపద",
    "style": "గేయం",
    "era": "సంప్రదాయ",
    "language": "telugu"
  },
  {
    "text": "అమ్మ కన్నీళ్లు అమృతం\nనాన్న చెమట బంగారం\nగురువు ఆశీర్వాదం వజ్రం\nస్నేహితుని నవ్వు ముత్యం",
    "title": "ఆధునిక కవిత 13",
    "author": "ఆధునిక కవి",
    "style": "వచన కవిత",
    "era": "21వ శతాబ్దం",
    "language": "telugu"
  },
  {
    "text": "ఆంధ్ర మహాభారతం\nఆదికవి నన్నయ రచన\nతెలుగు సాహిత్యానికి\nతొలి మహాకావ్యం",
    "title": "నన్నయ పద్యం 22",
    "author": "నన్నయ",
    "style": "మహాభారతం",
    "era": "11వ శతాబ్దం",
    "language": "telugu"
  },
  {
    "text": "ఉభయ కవి మిత్ర బిరుదం\nఉత్తమ కవిత్వ నిరూపణ\nతిక్కన సోమయాజి\nతెలుగు సాహిత్య ప్రభువు",
    "title": "తిక్కన పద్యం 12",
    "author": "తిక్కన",
    "style": "మహాభారతం",
    "era": "13వ శతాబ్దం",
    "language": "telugu"
  },
  {
    "text": "కనకపు సింహాసనము న కరిన శునకము\nమ్రొక్కులందరేల మూర్ఖులకు\nచెడుగువాని కెల్ల సేవ చేయనేల\nవిశ్వదాభిరామ వినురవేమ",
    "title": "వేమన పద్యం 10",
    "author": "వేమన",
    "style": "ఆట వెలది",
    "era": "18వ శతాబ్దం",
    "language": "telugu"
  },
  {
    "text": "మనసు నిలపి నా మనసును\nరామునిపై నిలిపి ధ్యానం\nఅనంత సుఖము పొందగలడు\nరామ భక్తుడు ధన్యుడు",
    "title": "త్యాగరాజ కీర్తన 6",
    "author": "త్యాగరాజు",
    "style": "కర్ణాటక సంగీతం",
    "era": "18వ శతాబ్దం",
    "language": "telugu"
  },
  {
    "text": "ప్రకృతి అందం చూడండి\nపచ్చని చెట్లు ఆస్వాదించండి\nపక్షుల పాట వినండి\nప్రకృతితో ప్రేమించండి",
    "title": "ఆధునిక కవిత 21",
    "author": "ఆధునిక కవి",
    "style": "వచన కవిత",
    "era": "21వ శతాబ్దం",
    "language": "telugu"
  },
  {
    "text": "ఉప్పు కప్పురంబు నొక్కపోలికనుండు\nచూడ చూడ రుచులు జాడ వేరు\nపురుషులందు పుణ్య పురుషులు వేరయా\nవిశ్వదాభిరామ వినురవేమ",
    "title": "వేమన పద్యం 1",
    "author": "వేమన",
    "style": "ఆట వెలది",
    "era": "18వ శతాబ్దం",
    "language": "telugu"
  },
  {
    "text": "పుట్టపర్తి బస్సులోన\nపుట్టిందమ్మ ఆ పిల్ల\nఎక్కడ పుట్టినా ఏమిటమ్మ\nఎద్దు ఎక్కడ దున్నినా ఏమిటమ్మ",
    "title": "గురజాడ కవిత 2",
    "author": "గురజాడ అప్పారావు",
    "style": "సామాజిక కవిత్వం",
    "era": "20వ శతాబ్దం",
    "language": "telugu"
  },
  {
    "text": "స్త్రీ విద్య అవసరం\nఆడపిల్లల చదువు ముఖ్యం\nసమాన హక్కులు కావాలి\nసమ సమాజం రావాలి",
    "title": "గురజాడ కవిత 7",
    "author": "గురజాడ అప్పారావు",
    "style": "సామాజిక కవిత్వం",
    "era": "20వ శతాబ్దం",
    "language": "telugu"
  },
  {
    "text": "సప్తగిరులందు వెలసిన స్వామికి\nసేవలందించేము సేవకులమయ్య\nశ్రీ వేంకటాచల పతికి నమస్కారము",
    "title": "అన్నమయ్య కీర్తన 13",
    "author": "అన్నమయ్య",
    "style": "సంకీర్తన",
    "era": "15వ శతాబ్దం",
    "language": "telugu"
  },
  {
    "text": "ఆలస్యము అమృతము విషము చేయు\nసమయపాలన సఫలత నిచ్చును",
    "title": "నీతి పద్యం 7",
    "author": "సంప్రదాయ",
    "style": "నీతి శతకం",
    "era": "సంప్రదాయ",
    "language": "telugu"
  },
  {
    "text": "రామ రామ రామ రామ\nశ్రీరామ జయ రామ\nరామ నామ జపం చేసి\nముక్తి పొందగలవయ్య",
    "title": "రామదాసు కీర్తన 5",
    "author": "రామదాసు",
    "style": "భక్తి కీర్తన",
    "era": "17వ శతాబ్దం",
    "language": "telugu"
  },
  {
    "text": "రాజరాజ నరేంద్రుడు\nరసజ్ఞుడైన పాలకుడు\nనన్నయను ఆదరించి\nమహాభారతం రచింపజేసెను",
    "title": "నన్నయ పద్యం 24",
    "author": "నన్నయ",
    "style": "మహాభారతం",
    "era": "11వ శతాబ్దం",
    "language": "telugu"
  },
  {
    "text": "అర్జునుని విషాదం\nకృష్ణుడు తొలగించెను\nగీతా బోధనతో\nధర్మ యుద్ధం చేసెను",
    "title": "తిక్కన పద్యం 3",
    "author": "తిక్కన",
    "style": "మహాభారతం",
    "era": "13వ శతాబ్దం",
    "language": "telugu"
  },
  {
    "text": "చిన్నతనపు స్నేహం చిరకాలం గుర్తుండు\nబాల్యపు ఆటలు బంగారం వంటివి\nస్కూలు రోజులు స్వర్గం వంటివి\nటీచర్ల ఆశీస్సులు తరతరాలుగా కాపాడు",
    "title": "ఆధునిక కవిత 8",
    "author": "ఆధునిక కవి",
    "style": "వచన కవిత",
    "era": "21వ శతాబ్దం",
    "language": "telugu"
  },
  {
    "text": "కలిమి గలవానికి కమలాలవాసము\nలేమి గలవానికి లేత మంచము\nధనము లేనివాని దాపరికము లేదు\nధనవంతుడు గొప్ప సుమతీ",
    "title": "సుమతీ శతకం 15",
    "author": "బద్దెన",
    "style": "కందం",
    "era": "14వ శతాబ్దం",
    "language": "telugu"
  },
  {
    "text": "శ్రీరఘువర నన్ను బ్రోవు\nసీతా రమణా రామచంద్రా\nపాహి పాహి కరుణతో\nభక్త వత్సలా రామా",
    "title": "త్యాగరాజ కీర్తన 15",
    "author": "త్యాగరాజు",
    "style": "కర్ణాటక సంగీతం",
    "era": "18వ శతాబ్దం",
    "language": "telugu"
  },
  {
    "text": "శ్రీమహాలక్ష్మి వక్షస్థలవాసా\nధనధాన్యములిచ్చు దయామయుడు\nలక్ష్మీకాంత నీవే లోక పాలకుడా",
    "title": "అన్నమయ్య కీర్తన 22",
    "author": "అన్నమయ్య",
    "style": "సంకీర్తన",
    "era": "15వ శతాబ్దం",
    "language": "telugu"
  },
  {
    "text": "పరమాత్మునికి బ్రతిమాలి\nపాప మోచనం పొందగలడు\nరామ నామం జపించేవారికి\nముక్తి మార్గం సులువు",
    "title": "త్యాగరాజ కీర్తన 12",
    "author": "త్యాగరాజు",
    "style": "కర్ణాటక సంగీతం",
    "era": "18వ శతాబ్దం",
    "language": "telugu"
  },
  {
    "text": "రామదాసు కీర్తనలు రసమయంగా\nభక్తి భావాలు భాసిల్లుతూ\nతెలుగు నేలను తేజోవంతం చేసెను\nరామ నామ గానంతో",
    "title": "రామదాసు కీర్తన 18",
    "author": "రామదాసు",
    "style": "భక్తి కీర్తన",
    "era": "17వ శతాబ్దం",
    "language": "telugu"
  },
  {
    "text": "అల్పుడెపుడు పల్కు నాడంబరముగాను\nసజ్జనుండు పల్కు చల్లగాను\nకంచుమ్రోగునట్లు కనకంబు మ్రోగునా\nవిశ్వదాభిరామ వినురవేమ",
    "title": "వేమన పద్యం 2",
    "author": "వేమన",
    "style": "ఆట వెలది",
    "era": "18వ శతాబ్దం",
    "language": "telugu"
  },
  {
    "text": "హాస్య రచనలలో హరివిల్లు\nవ్యంగ్య రచనలలో వజ్రాయుధం\nచిలకమర్తి కలం\nచతురంగా పనిచేసెను",
    "title": "చిలకమర్తి రచన 23",
    "author": "చిలకమర్తి",
    "style": "హాస్య కవిత్వం",
    "era": "20వ శతాబ్దం",
    "language": "telugu"
  },
  {
    "text": "ఆనందమే హ్రాదయమందు నిండెను\nవేంకటేశు దర్శనమందు ఆనందము\nభక్తి భావమందు భగవంతుని చూసితి",
    "title": "అన్నమయ్య కీర్తన 11",
    "author": "అన్నమయ్య",
    "style": "సంకీర్తన",
    "era": "15వ శతాబ్దం",
    "language": "telugu"
  },
  {
    "text": "శివరాత్రి మహాత్మ్యం\nశివుని పూజ విధానం\nవ్రత మహిమ\nభక్తి ఫలితం",
    "title": "శ్రీనాథ పద్యం 8",
    "author": "శ్రీనాథుడు",
    "style": "ప్రబంధం",
    "era": "15వ శతాబ్దం",
    "language": "telugu"
  },
  {
    "text": "రాజుకు రాజ్యమే ధనం\nపండితునికి విద్యే ధనం\nరైతుకు భూమి ధనం\nఎవరికి వారి ధనం గొప్ప",
    "title": "భర్తృహరి సుభాషితం 15",
    "author": "భర్తృహరి",
    "style": "సుభాషిత శతకం",
    "era": "ప్రాచీన",
    "language": "telugu"
  },
  {
    "text": "కాలం మారినా కవిత్వం నిలిచింది\nశ్రీశ్రీ రచనలు శాశ్వతంగా ఉన్నాయి\nప్రజల మనసుల్లో ప్రతిధ్వనిస్తూ\nప్రజా కవిగా నిలిచాడు",
    "title": "శ్రీశ్రీ కవిత 24",
    "author": "శ్రీశ్రీ",
    "style": "అభ్యుదయ కవిత్వం",
    "era": "20వ శతాబ్దం",
    "language": "telugu"
  },
  {
    "text": "చంపూ కావ్య శైలిలో\nచమత్కార పద్యాలు చెప్పెను\nగద్య పద్య మిశ్రమంలో\nగంభీరమైన రచన చేసెను",
    "title": "నన్నయ పద్యం 7",
    "author": "నన్నయ",
    "style": "మహాభారతం",
    "era": "11వ శతాబ్దం",
    "language": "telugu"
  },
  {
    "text": "ఖడ్గ సృష్టి కవిత\nకత్తి వంటి మాటలు\nదురాచారాలపై దాడి\nధైర్యంగా చేసాడు",
    "title": "శ్రీశ్రీ కవిత 14",
    "author": "శ్రీశ్రీ",
    "style": "అభ్యుదయ కవిత్వం",
    "era": "20వ శతాబ్దం",
    "language": "telugu"
  },
  {
    "text": "ధైర్యం ఉన్నవాడికి అసాధ్యం లేదు\nసహనం ఉన్నవాడికి కష్టం లేదు\nవిద్య ఉన్నవాడికి అజ్ఞానం లేదు\nభర్తృహరి ధైర్య వాక్యం",
    "title": "భర్తృహరి సుభాషితం 20",
    "author": "భర్తృహరి",
    "style": "సుభాషిత శతకం",
    "era": "ప్రాచీన",
    "language": "telugu"
  },
  {
    "text": "జాతి మతము చూడక జనములను ప్రేమించు\nమానవత్వమొక్కటే మార్గదర్శి\nకులము గోత్రమేదైన గుణము ముఖ్యము\nమంచి గుణము గొప్ప సుమతీ",
    "title": "సుమతీ శతకం 19",
    "author": "బద్దెన",
    "style": "కందం",
    "era": "14వ శతాబ్దం",
    "language": "telugu"
  },
  {
    "text": "చిప్పలోన పడ్డ చినుకు ముత్యము గాను\nసముద్రమందుబడ్డ శంఖవర్ణము\nబ్రహ్మయందు చేరు పగులు రూపు గాదు\nవిశ్వదాభిరామ వినురవేమ",
    "title": "వేమన పద్యం 6",
    "author": "వేమన",
    "style": "ఆట వెలది",
    "era": "18వ శతాబ్దం",
    "language": "telugu"
  },
  {
    "text": "స్త్రీల స్థితిని చూపించెను\nసమాజ దురాచారాలు ఎత్తి చూపెను\nమార్పు కోసం పిలుపునిచ్చెను\nగురజాడ సాహిత్య సేవ",
    "title": "గురజాడ కవిత 14",
    "author": "గురజాడ అప్పారావు",
    "style": "సామాజిక కవిత్వం",
    "era": "20వ శతాబ్దం",
    "language": "telugu"
  },
  {
    "text": "కలవాని జేసేను కమలాక్షుడు\nబలవంతుని జేసేను భక్తవత్సలుడు\nకులదేవత నీవయ్య కొలిచేము నిన్ను\nఫలమిచ్చు దేవుడవు పట్టాభిరాముడ",
    "title": "భాగవత పద్యం 4",
    "author": "పోతన",
    "style": "ఉత్పలమాల",
    "era": "15వ శతాబ్దం",
    "language": "telugu"
  },
  {
    "text": "దేశమును ప్రేమించుమన్నా\nమంచి అన్నది పెంచుమన్నా\nవట్టి మాటలు కట్టిపెట్టి\nగట్టి మేలు తలపెట్టవయ్యా",
    "title": "గురజాడ కవిత 1",
    "author": "గురజాడ అప్పారావు",
    "style": "సామాజిక కవిత్వం",
    "era": "20వ శతాబ్దం",
    "language": "telugu"
  },
  {
    "text": "ప్రబంధ యుగంలో ప్రథమ కవిగా నిలిచెను\nశృంగార రసంలో శిఖరాగ్రం చేరెను\nకావ్యకళలో కుశలత చూపెను\nశ్రీనాథుడు సాహిత్య శిఖామణి",
    "title": "శ్రీనాథ పద్యం 25",
    "author": "శ్రీనాథుడు",
    "style": "ప్రబంధం",
    "era": "15వ శతాబ్దం",
    "language": "telugu"
  },
  {
    "text": "ఏ తీరుగ నను దయ చూసేవో\nశ్రీరామచంద్ర నన్ను గావు\nపతిత పావనా రామా\nదీన బంధో దయానిధే",
    "title": "రామదాసు కీర్తన 1",
    "author": "రామదాసు",
    "style": "భక్తి కీర్తన",
    "era": "17వ శతాబ్దం",
    "language": "telugu"
  },
  {
    "text": "నిజాయితీగా బ్రతుకు నిలకడగా ఉండు\nమోసం చేయకు మంచిగా ఉండు",
    "title": "నీతి పద్యం 11",
    "author": "సంప్రదాయ",
    "style": "నీతి శతకం",
    "era": "సంప్రదాయ",
    "language": "telugu"
  },
  {
    "text": "క్షమించడం నేర్చుకో క్షేమం కలుగు\nపగ పెట్టుకుంటే పతనమవుతావు",
    "title": "నీతి పద్యం 13",
    "author": "సంప్రదాయ",
    "style": "నీతి శతకం",
    "era": "సంప్రదాయ",
    "language": "telugu"
  },
  {
    "text": "అన్నదానమంత ఆత్మకు సుఖమిచ్చు\nవిద్యాదానమంత విజ్ఞానమిచ్చు\nదానధర్మములకు తరుణోపాయము లేదు\nవిశ్వదాభిరామ వినురవేమ",
    "title": "వేమన పద్యం 33",
    "author": "వేమన",
    "style": "ఆట వెలది",
    "era": "18వ శతాబ్దం",
    "language": "telugu"
  },
  {
    "text": "పదహారు పర్వాలు పద్యాలలో రచించెను\nమహాభారత సారం మనకు అందించెను\nకవిత్రయంలో కమనీయ కవిగా\nతిక్కన సోమయాజి తెలుగు వెలుగు",
    "title": "తిక్కన పద్యం 11",
    "author": "తిక్కన",
    "style": "మహాభారతం",
    "era": "13వ శతాబ్దం",
    "language": "telugu"
  },
  {
    "text": "ధర్మరాజు ధర్మాన్ని\nభీముని శక్తిని\nఅర్జునుని విలువిద్యను\nనన్నయ కవిత్వంలో చూపెను",
    "title": "నన్నయ పద్యం 8",
    "author": "నన్నయ",
    "style": "మహాభారతం",
    "era": "11వ శతాబ్దం",
    "language": "telugu"
  },
  {
    "text": "కురు పాండవ యుద్ధం\nకురుక్షేత్రంలో జరిగిన వృత్తాంతం\nనన్నయ కావ్యంలో\nనయనానందంగా చూపెను",
    "title": "నన్నయ పద్యం 10",
    "author": "నన్నయ",
    "style": "మహాభారతం",
    "era": "11వ శతాబ్దం",
    "language": "telugu"
  },
  {
    "text": "చేయవలసిం కార్యం చేయాలి\nచేయకూడని కార్యం చేయకూడదు\nధర్మం తెలిసి నడవాలి\nభర్తృహరి ధర్మ బోధన",
    "title": "భర్తృహరి సుభాషితం 14",
    "author": "భర్తృహరి",
    "style": "సుభాషిత శతకం",
    "era": "ప్రాచీన",
    "language": "telugu"
  },
  {
    "text": "జయమంగళం నిత్య శుభమంగళం\nశ్రీ వేంకటేశ్వర స్వామికి జయమంగళం\nఏడుకొండలవాడ జయమంగళం",
    "title": "అన్నమయ్య కీర్తన 9",
    "author": "అన్నమయ్య",
    "style": "సంకీర్తన",
    "era": "15వ శతాబ్దం",
    "language": "telugu"
  },
  {
    "text": "గొడ్డుగొడ్డు పాలు గొబ్బరి కాయలు\nమంచి మంచి పండ్లు మధురమైన తేనె\nపసిబిడ్డలకు పాలు పథ్యమైన భోజనం\nఆరోగ్యమే ధనము సుమతీ",
    "title": "సుమతీ శతకం 17",
    "author": "బద్దెన",
    "style": "కందం",
    "era": "14వ శతాబ్దం",
    "language": "telugu"
  },
  {
    "text": "సోమరితనమంత సొంతము కాదయ్య\nపనికి వెళ్ళకున్న పాపమవుట\nకష్టపడిన వాడే కడు సుఖపడు\nవిశ్వదాభిరామ వినురవేమ",
    "title": "వేమన పద్యం 25",
    "author": "వేమన",
    "style": "ఆట వెలది",
    "era": "18వ శతాబ్దం",
    "language": "telugu"
  },
  {
    "text": "కడుపులోన దాచి కష్టపడి పెంచిన\nతల్లిదండ్రి సేవ తప్పకుండ చేయవలె\nగురువు మాట వినకపోతె గొప్ప కాదు\nనెలతల్లికి నమస్కారం సుమతీ",
    "title": "సుమతీ శతకం 7",
    "author": "బద్దెన",
    "style": "కందం",
    "era": "14వ శతాబ్దం",
    "language": "telugu"
  },
  {
    "text": "జగదానంద కారక\nజయ జానకీ ప్రాణ నాయక\nశుభదాయక రామా\nరఘుకుల తిలక",
    "title": "త్యాగరాజ కీర్తన 8",
    "author": "త్యాగరాజు",
    "style": "కర్ణాటక సంగీతం",
    "era": "18వ శతాబ్దం",
    "language": "telugu"
  },
  {
    "text": "రాగసుధారస పానమిది\nరామనామ సంకీర్తనం\nసంగీతమందు సారమిది\nత్యాగరాజ స్వామి వందనం",
    "title": "త్యాగరాజ కీర్తన 16",
    "author": "త్యాగరాజు",
    "style": "కర్ణాటక సంగీతం",
    "era": "18వ శతాబ్దం",
    "language": "telugu"
  },
  {
    "text": "బ్రహ్మకడిగిన పాదము\nబ్రహ్మము తానైన పాదము\nఅమ్మకూ అమ్మ ఇచ్చిన పాదము\nఇందఱి కెల్లను కొంగ బంగారము",
    "title": "అన్నమయ్య కీర్తన 1",
    "author": "అన్నమయ్య",
    "style": "సంకీర్తన",
    "era": "15వ శతాబ్దం",
    "language": "telugu"
  },
  {
    "text": "మహాకవులలో మాణిక్యం\nభావ కవులలో భాస్కరం\nకృష్ణశాస్త్రి కీర్తి\nకావ్య లోకంలో శాశ్వతం",
    "title": "కృష్ణశాస్త్రి కవిత 23",
    "author": "దేవులపల్లి కృష్ణశాస్త్రి",
    "style": "భావ కవిత్వం",
    "era": "20వ శతాబ్దం",
    "language": "telugu"
  },
  {
    "text": "ధనం పోతే తిరిగి వస్తుంది\nమానం పోతే తిరిగి రాదు\nమానం కాపాడుకొనే మార్గంలో\nధనం పోయినా పర్వాలేదు",
    "title": "భర్తృహరి సుభాషితం 12",
    "author": "భర్తృహరి",
    "style": "సుభాషిత శతకం",
    "era": "ప్రాచీన",
    "language": "telugu"
  },
  {
    "text": "స్నేహాన్ని కాపాడు స్నేహితుని గౌరవించు\nమంచి మిత్రుడు మాణిక్యం వంటివాడు",
    "title": "నీతి పద్యం 20",
    "author": "సంప్రదాయ",
    "style": "నీతి శతకం",
    "era": "సంప్రదాయ",
    "language": "telugu"
  },
  {
    "text": "భీష్ముని ప్రతిజ్ఞ\nద్రోణుని గురుత్వం\nకర్ణుని దానశీలత\nధృతరాష్ట్రుని అంధత్వం",
    "title": "తిక్కన పద్యం 4",
    "author": "తిక్కన",
    "style": "మహాభారతం",
    "era": "13వ శతాబ్దం",
    "language": "telugu"
  },
  {
    "text": "హరవిలాసము కావ్యం\nశ్రీనాథుని రచన\nశృంగార రసం\nకావ్య సౌందర్యం",
    "title": "శ్రీనాథ పద్యం 5",
    "author": "శ్రీనాథుడు",
    "style": "ప్రబంధం",
    "era": "15వ శతాబ్దం",
    "language": "telugu"
  },
  {
    "text": "ద్రౌపది మానం\nపాండవులు కాపాడిరి\nకృష్ణుని అనుగ్రహం\nధర్మం నిలబెట్టిరి",
    "title": "తిక్కన పద్యం 5",
    "author": "తిక్కన",
    "style": "మహాభారతం",
    "era": "13వ శతాబ్దం",
    "language": "telugu"
  },
  {
    "text": "గజేంద్ర మోక్షము గొప్ప కథ\nమొసలి బారిన మూగిన ఏనుగు\nహరిని స్మరించి హరిని చేరెను\nభక్తి మహిమ భగవంతుని కృప",
    "title": "భాగవత పద్యం 10",
    "author": "పోతన",
    "style": "ఉత్పలమాల",
    "era": "15వ శతాబ్దం",
    "language": "telugu"
  },
  {
    "text": "బానిసత్వం వదిలిపెట్టి\nస్వేచ్ఛ పొందమని పిలుపు\nదేశ భక్తి పెంపొందించు\nజాతి జాగృతి రగిలించు",
    "title": "గురజాడ కవిత 6",
    "author": "గురజాడ అప్పారావు",
    "style": "సామాజిక కవిత్వం",
    "era": "20వ శతాబ్దం",
    "language": "telugu"
  },
  {
    "text": "నన్నయ భట్టు మహాకవి\nతెలుగు సాహిత్య పితామహుడు\nఆదికవి బిరుదం పొంది\nఆంధ్ర భాషను వెలిగించెను",
    "title": "నన్నయ పద్యం 25",
    "author": "నన్నయ",
    "style": "మహాభారతం",
    "era": "11వ శతాబ్దం",
    "language": "telugu"
  },
  {
    "text": "ఇది శ్రీమద్భాగవతము\nఇది వేదాంత సారం\nఇది పరమ పురుషుని లీల\nఇది భక్తి మార్గ దీపం",
    "title": "భాగవత పద్యం 2",
    "author": "పోతన",
    "style": "ఉత్పలమాల",
    "era": "15వ శతాబ్దం",
    "language": "telugu"
  },
  {
    "text": "గేయ కవితల్లో గొప్పతనం\nగద్య కవితల్లో గంభీరత\nశ్రీశ్రీ రచనలలో\nశ్రమజీవుల గళం",
    "title": "శ్రీశ్రీ కవిత 18",
    "author": "శ్రీశ్రీ",
    "style": "అభ్యుదయ కవిత్వం",
    "era": "20వ శతాబ్దం",
    "language": "telugu"
  },
  {
    "text": "తల్లిదండ్రులను గౌరవించు\nగురువులను పూజించు\nపెద్దలను మన్నించు\nఇదే నీతి మార్గం",
    "title": "భర్తృహరి సుభాషితం 24",
    "author": "భర్తృహరి",
    "style": "సుభాషిత శతకం",
    "era": "ప్రాచీన",
    "language": "telugu"
  },
  {
    "text": "కొండలలో నెలకొన్న గోవిందా\nకూరిమితో నన్ను గావు గోవిందా\nతొండమువాని తమ్ముడా గోవిందా\nతొల్లి నీకు మ్రొక్కేదము గోవిందా",
    "title": "అన్నమయ్య కీర్తన 4",
    "author": "అన్నమయ్య",
    "style": "సంకీర్తన",
    "era": "15వ శతాబ్దం",
    "language": "telugu"
  },
  {
    "text": "తెలుగు భాషకు తేజస్సు నిచ్చెను\nకావ్యాలందు కమనీయత చూపెను\nపద్యాలందు పటుత్వం ప్రదర్శించెను\nశ్రీనాథుడు తెలుగు సాహిత్య వైభవం",
    "title": "శ్రీనాథ పద్యం 20",
    "author": "శ్రీనాథుడు",
    "style": "ప్రబంధం",
    "era": "15వ శతాబ్దం",
    "language": "telugu"
  },
  {
    "text": "రామదాసు హృదయంలో\nరాముడే నివసించు\nభక్తి మార్గం చూపించు\nముక్తి మార్గం తెలిపించు",
    "title": "రామదాసు కీర్తన 10",
    "author": "రామదాసు",
    "style": "భక్తి కీర్తన",
    "era": "17వ శతాబ్దం",
    "language": "telugu"
  },
  {
    "text": "పెద్దల మాట వినుము పెన్నిధి వంటిది\nపిన్నలను గౌరవించు పూజ్యంగా చూడు",
    "title": "నీతి పద్యం 18",
    "author": "సంప్రదాయ",
    "style": "నీతి శతకం",
    "era": "సంప్రదాయ",
    "language": "telugu"
  },
  {
    "text": "ఉపచారము చేయు వారు\nరాముని భక్తులు సుఖులు\nసేవలో తరించేవారికి\nరామ దర్శనం లభించు",
    "title": "త్యాగరాజ కీర్తన 11",
    "author": "త్యాగరాజు",
    "style": "కర్ణాటక సంగీతం",
    "era": "18వ శతాబ్దం",
    "language": "telugu"
  },
  {
    "text": "పన్నెండేళ్ళు చెరసాలలో\nపడ్డా రాముణ్ని వీడలేదు\nభక్తి బంధంలో బంధించబడి\nభద్రాచల రాముని చేరెను",
    "title": "రామదాసు కీర్తన 16",
    "author": "రామదాసు",
    "style": "భక్తి కీర్తన",
    "era": "17వ శతాబ్దం",
    "language": "telugu"
  },
  {
    "text": "కృష్ణశాస్త్రి కవిత్వం\nకాలం మారినా కమనీయం\nతరతరాలకు తేజస్సుగా\nతెలుగు సాహిత్యంలో నిలిచెను",
    "title": "కృష్ణశాస్త్రి కవిత 25",
    "author": "దేవులపల్లి కృష్ణశాస్త్రి",
    "style": "భావ కవిత్వం",
    "era": "20వ శతాబ్దం",
    "language": "telugu"
  },
  {
    "text": "వెన్నెల రాత్రులు\nపున్నమి చందమామ\nకృష్ణశాస్త్రి పద్యాలలో\nకాంతులు వెదజల్లును",
    "title": "కృష్ణశాస్త్రి కవిత 17",
    "author": "దేవులపల్లి కృష్ణశాస్త్రి",
    "style": "భావ కవిత్వం",
    "era": "20వ శతాబ్దం",
    "language": "telugu"
  },
  {
    "text": "సామాజిక న్యాయం కోసం\nసాహిత్యంలో పోరాడెను\nపేదల కోసం ప్రజల కోసం\nపలికిన గొంతు గురజాడ",
    "title": "గురజాడ కవిత 21",
    "author": "గురజాడ అప్పారావు",
    "style": "సామాజిక కవిత్వం",
    "era": "20వ శతాబ్దం",
    "language": "telugu"
  },
  {
    "text": "పంట చేలో పనులు చేసి\nరైతన్న బతుకుతాడు\nవర్షం వస్తే వరదలొస్తే\nకష్టపడుతూ ఉంటాడు",
    "title": "జానపద గేయం 14",
    "author": "జానపద",
    "style": "గేయం",
    "era": "సంప్రదాయ",
    "language": "telugu"
  },
  {
    "text": "పెద్దలొద్ద మాట పెడచెవిన బెట్టకు\nపిన్నలొద్ద గొప్ప పెరగకుండ\nసమయమెరిగి నడుచు సజ్జనుడు గొప్ప\nవిశ్వదాభిరామ వినురవేమ",
    "title": "వేమన పద్యం 34",
    "author": "వేమన",
    "style": "ఆట వెలది",
    "era": "18వ శతాబ్దం",
    "language": "telugu"
  },
  {
    "text": "కృష్ణావతారము కమనీయమైనది\nయశోదమ్మ ఒడిలో యదుకుల తిలకుడు\nగోపికలతో గోవులతో గోకులమందు\nలీలలతో లోకము లాలించెను",
    "title": "భాగవత పద్యం 13",
    "author": "పోతన",
    "style": "ఉత్పలమాల",
    "era": "15వ శతాబ్దం",
    "language": "telugu"
  },
  {
    "text": "వినయంగా మాట్లాడు విజయం సాధించు\nగర్వంగా మాట్లాడితే గౌరవం తగ్గును",
    "title": "నీతి పద్యం 21",
    "author": "సంప్రదాయ",
    "style": "నీతి శతకం",
    "era": "సంప్రదాయ",
    "language": "telugu"
  },
  {
    "text": "చిన్నప్పటి కలలు\nపెద్దయినా గుర్తుండు\nకలల్ని సాధించాలి\nజీవితం సార్థకం",
    "title": "ఆధునిక కవిత 17",
    "author": "ఆధునిక కవి",
    "style": "వచన కవిత",
    "era": "21వ శతాబ్దం",
    "language": "telugu"
  },
  {
    "text": "శ్రామిక వర్గం గళం\nశ్రీశ్రీ కవిత్వంలో\nప్రతిధ్వనించెను గట్టిగా\nప్రజా కవిగా నిలిచెను",
    "title": "శ్రీశ్రీ కవిత 8",
    "author": "శ్రీశ్రీ",
    "style": "అభ్యుదయ కవిత్వం",
    "era": "20వ శతాబ్దం",
    "language": "telugu"
  },
  {
    "text": "పెద్దలకు నమస్కారం పిల్లలకు ఆశీస్సులు\nపండగ వచ్చినప్పుడు పరస్పర గౌరవం\nసంప్రదాయాలందు సంతోషమందు",
    "title": "జానపద గేయం 23",
    "author": "జానపద",
    "style": "గేయం",
    "era": "సంప్రదాయ",
    "language": "telugu"
  },
  {
    "text": "దయ లేని వాడు దరిద్రుడు అవును\nక్షమ లేని వాడు క్షీణించు\nశాంతము లేని వాడు చచ్చిపోవును\nవిశ్వదాభిరామ వినురవేమ",
    "title": "వేమన పద్యం 29",
    "author": "వేమన",
    "style": "ఆట వెలది",
    "era": "18వ శతాబ్దం",
    "language": "telugu"
  },
  {
    "text": "టెక్నాలజీ అభివృద్ధి\nప్రపంచం మారుతోంది\nడిజిటల్ యుగంలో\nమానవత్వం కాపాడండి",
    "title": "ఆధునిక కవిత 22",
    "author": "ఆధునిక కవి",
    "style": "వచన కవిత",
    "era": "21వ శతాబ్దం",
    "language": "telugu"
  },
  {
    "text": "భావ కవిత్వంలో భాస్కరుడు\nదేవులపల్లి కృష్ణశాస్త్రి\nతెలుగు కవిత్వంలో తేజోమూర్తి\nప్రకృతి వర్ణనలో ప్రథముడు",
    "title": "కృష్ణశాస్త్రి కవిత 11",
    "author": "దేవులపల్లి కృష్ణశాస్త్రి",
    "style": "భావ కవిత్వం",
    "era": "20వ శతాబ్దం",
    "language": "telugu"
  },
  {
    "text": "పద్య కవిత్వంలో ప్రథమ ప్రయోగం\nప్రబంధ యుగానికి ప్రారంభం\nనన్నయ మహాకవి\nనూతన మార్గ నిర్మాత",
    "title": "నన్నయ పద్యం 18",
    "author": "నన్నయ",
    "style": "మహాభారతం",
    "era": "11వ శతాబ్దం",
    "language": "telugu"
  },
  {
    "text": "దేశభక్తి గేయాలలో\nదేశమును ప్రేమించుమన్నా\nఉత్తేజకరమైన పిలుపు\nజాతి జాగృతి కావాలని",
    "title": "గురజాడ కవిత 16",
    "author": "గురజాడ అప్పారావు",
    "style": "సామాజిక కవిత్వం",
    "era": "20వ శతాబ్దం",
    "language": "telugu"
  },
  {
    "text": "కృష్ణపక్షం కావ్యంలో\nచంద్రుని వర్ణనలు\nతారల సౌందర్యం\nకృష్ణశాస్త్రి కలం మహిమ",
    "title": "కృష్ణశాస్త్రి కవిత 13",
    "author": "దేవులపల్లి కృష్ణశాస్త్రి",
    "style": "భావ కవిత్వం",
    "era": "20వ శతాబ్దం",
    "language": "telugu"
  },
  {
    "text": "శ్రీశ్రీ మహాకవి\nశ్రమజీవుల గళం\nతెలుగు సాహిత్యంలో\nతేజోమూర్తి శాశ్వతం",
    "title": "శ్రీశ్రీ కవిత 25",
    "author": "శ్రీశ్రీ",
    "style": "అభ్యుదయ కవిత్వం",
    "era": "20వ శతాబ్దం",
    "language": "telugu"
  },
  {
    "text": "రాధాకృష్ణుల ప్రేమ రసమయమైనది\nగోపికలతో గోవిందుని రాసలీల\nబృందావనమందు బంగారు జ్ఞాపకాలు\nమధురభక్తి మార్గము మనకు చూపు",
    "title": "భాగవత పద్యం 14",
    "author": "పోతన",
    "style": "ఉత్పలమాల",
    "era": "15వ శతాబ్దం",
    "language": "telugu"
  },
  {
    "text": "తెలుగు సాహిత్య చరిత్రలో\nతొలి వచన సాహిత్యకారులలో\nచిలకమర్తి లక్ష్మీనరసింహం\nచిరస్థాయి కీర్తి గడించెను",
    "title": "చిలకమర్తి రచన 25",
    "author": "చిలకమర్తి",
    "style": "హాస్య కవిత్వం",
    "era": "20వ శతాబ్దం",
    "language": "telugu"
  },
  {
    "text": "కవిత్వంలో కమనీయత\nపద్యంలో పటుత్వం\nరచనలో రమణీయత\nశ్రీనాథుని శైలి శ్రేష్ఠం",
    "title": "శ్రీనాథ పద్యం 22",
    "author": "శ్రీనాథుడు",
    "style": "ప్రబంధం",
    "era": "15వ శతాబ్దం",
    "language": "telugu"
  },
  {
    "text": "బాలసాహిత్యంలో బంగారు నిధి\nపిల్లలకు కథలు పలికెను\nబోధన భావాలతో బాల్యాన్ని తీర్చెను\nచిలకమర్తి బాల సాహిత్య సేవ",
    "title": "చిలకమర్తి రచన 20",
    "author": "చిలకమర్తి",
    "style": "హాస్య కవిత్వం",
    "era": "20వ శతాబ్దం",
    "language": "telugu"
  },
  {
    "text": "అభ్యుదయ రచయితల సంఘంలో\nఆద్యుడుగా నిలిచాడు\nప్రగతిశీల భావాలతో\nప్రజలను మేల్కొలిపాడు",
    "title": "శ్రీశ్రీ కవిత 20",
    "author": "శ్రీశ్రీ",
    "style": "అభ్యుదయ కవిత్వం",
    "era": "20వ శతాబ్దం",
    "language": "telugu"
  },
  {
    "text": "వేశ్య వృత్తి వదిలిపెట్టి\nమంచి బ్రతుకు బ్రతకవచ్చు\nసమాజం మారాలి\nమనసులు మారాలి",
    "title": "గురజాడ కవిత 4",
    "author": "గురజాడ అప్పారావు",
    "style": "సామాజిక కవిత్వం",
    "era": "20వ శతాబ్దం",
    "language": "telugu"
  },
  {
    "text": "తిరుమల వాసా దేవా దివ్య చరణా\nనీ పాదసేవలో ధన్యత పొందితి\nకైంకర్యమందు కరుణ చూపించు",
    "title": "అన్నమయ్య కీర్తన 18",
    "author": "అన్నమయ్య",
    "style": "సంకీర్తన",
    "era": "15వ శతాబ్దం",
    "language": "telugu"
  },
  {
    "text": "తెలుగు నవలా సాహిత్యంలో\nతొలితరం రచయితలలో ఒకరు\nచిలకమర్తి సేవలు\nచిరస్థాయిగా నిలిచాయి",
    "title": "చిలకమర్తి రచన 22",
    "author": "చిలకమర్తి",
    "style": "హాస్య కవిత్వం",
    "era": "20వ శతాబ్దం",
    "language": "telugu"
  },
  {
    "text": "నెల్లూరు వాసి నేలపై వెలిగెను\nమహాభారతంలో మాణిక్యాలు దాచెను\nకవిత్వ రత్నాలు కావ్యాలలో నింపెను\nతిక్కన సోమయాజి సాహిత్య శిఖరం",
    "title": "తిక్కన పద్యం 17",
    "author": "తిక్కన",
    "style": "మహాభారతం",
    "era": "13వ శతాబ్దం",
    "language": "telugu"
  },
  {
    "text": "మంచి నీళ్ళు త్రాగు మంచి భోజనముండు\nమంచి ఆరోగ్యము మరణము లేదు\nఆరోగ్యమే సంపద అది గ్రహించు\nవిశ్వదాభిరామ వినురవేమ",
    "title": "వేమన పద్యం 37",
    "author": "వేమన",
    "style": "ఆట వెలది",
    "era": "18వ శతాబ్దం",
    "language": "telugu"
  }
]